Workbook

Sheet About
A1: Precast Cost and Sourcing Analysis
A2: Learning project with synthetic data for a fictional precast concrete manufacturer, Northfield Precast Ltd. No real company data is used.
A4: Purpose | B4: Connect products, bills of materials, suppliers and sales to answer: what does each product cost to make, where does the material come from, and which data needs fixing?
A6: Sheet | B6: What it contains
A7: Assumptions | B7: Exchange rates, unit conversions, thresholds and key assumptions (inputs).
A8: Items | B8: Finished products: list price, conversion cost, HS code. Raw data + checks.
A9: Suppliers | B9: Supplier list with country and lead time.
A10: Components | B10: Purchased materials and parts with cost, supplier and origin. Raw data + checks.
A11: BOM | B11: Bill of materials lines. Looks up cost and origin, converts units, flags issues.
A12: Sales | B12: 2025 invoice lines. Adds category, revenue, discount and cost of sales.
A13: Cost_Rollup | B13: Unit cost per product vs. average selling price: margin and cost-to-price ratio.
A14: Sourcing | B14: 2025 material spend by origin country and by supplier, with reconciliation checks.
A15: Summary | B15: Revenue, cost of sales and margin by category and ship-to country.
A16: Data_Quality | B16: Count of every flagged issue, with severity and a suggested action.
A17: Open_Questions | B17: Log of questions to resolve with other teams.
A19: Colour guide
A20: Blue text | B20: Hardcoded input (raw data or an assumption).
A21: Black text | B21: Formula.
A22: Green text | B22: Direct link to another sheet.
A23: Yellow fill | B23: Key assumption you can change on the Assumptions sheet.
A24: Dark blue header | B24: Raw data column (as received).
A25: Grey-blue header | B25: Calculated column added in this workbook.
A26: Red / green fill | B26: Status CHECK (needs review) / OK.
A28: Rebuild | B28: python scripts/generate_data.py then python scripts/build_workbook.py

Sheet Assumptions
A1: Assumptions and Settings
A2: Yellow cells are inputs. Change them here and every sheet updates.
B4: Exchange rates to CAD
B5: Currency | C5: Rate to CAD | D5: Note
B6: CAD | C6: 1 | D6: Base currency
B7: USD | C7: 1.37 | D7: Assumed average 2025 rate (illustrative)
B8: EUR | C8: 1.5 | D8: Assumed average 2025 rate (illustrative)
B11: Unit conversions
B12: Key (formula) | C12: From unit | D12: To unit | E12: Factor | F12: Note
B13: =C13&">"&D13 -> LB>KG | C13: LB | D13: KG | E13: 0.45359237 | F13: 1 lb = 0.45359237 kg
B14: =C14&">"&D14 -> G>KG | C14: G | D14: KG | E14: 0.001 | F14: 1 g = 0.001 kg
B15: =C15&">"&D15 -> KG>T | C15: KG | D15: T | E15: 0.001 | F15: 1 kg = 0.001 tonne
B18: Thresholds and settings
B19: Home country code | C19: CA | D19: Used to split material cost into Domestic / Imported
B20: Sales discount flag (vs list price) | C20: 0.2 | D20: Sales lines priced lower than this are flagged
B21: Long lead time flag (days) | C21: 30 | D21: Suppliers above this lead time are flagged
B24: Key assumptions
B25: A1. | C25: All data in this workbook is synthetic (invented) and is used for learning only.
B26: A2. | C26: Unit costs are latest purchase prices, converted to CAD with the rates above.
B27: A3. | C27: Conversion cost (labour + plant overhead) per item is an estimate held on the Items sheet.
B28: A4. | C28: Concrete quantities use one simplified mix design per cubic metre for all products.
B29: A5. | C29: If a component code appears twice, lookups use the FIRST row. Duplicates are flagged on Components.
B30: A6. | C30: BOM lines with a missing cost are left out of material cost and flagged as 'Incomplete'.
B31: A7. | C31: HS codes are illustrative and must be confirmed before any real use.
B32: A8. | C32: Average selling price uses only 2025 invoice lines that have a price.

Sheet Items
A1: item_no | B1: description | C1: category | D1: uom | E1: hs_code | F1: list_price_cad | G1: conversion_cost_cad | H1: item_key | I1: issues | J1: status
A2: PC-RCP-0600 | B2: Reinforced concrete pipe 600 mm x 2.44 m | C2: Pipe | D2: EA | E2: 6810.91 | F2: 640 | G2: 310 | H2: =UPPER(TRIM(A2)) -> PC-RCP-0600 | I2: =IF(OR(E2="",LEN(E2)<>7,MID(E2,5,1)<>"."),"HS code missing/format; ","")&IF(COUNTIF($H$2:$H$500,H2)>1,"Duplicate item; ","") | J2: =IF(I2="","OK","CHECK") -> OK
A3: PC-RCP-0900 | B3: Reinforced concrete pipe 900 mm x 2.44 m | C3: Pipe | D3: EA | E3: 6810.91 | F3: 1150 | G3: 540 | H3: =UPPER(TRIM(A3)) -> PC-RCP-0900 | I3: =IF(OR(E3="",LEN(E3)<>7,MID(E3,5,1)<>"."),"HS code missing/format; ","")&IF(COUNTIF($H$2:$H$500,H3)>1,"Duplicate item; ","") | J3: =IF(I3="","OK","CHECK") -> OK
A4: PC-RCP-1200 | B4: Reinforced concrete pipe 1200 mm x 2.44 m | C4: Pipe | D4: EA | E4: 6810.91 | F4: 1890 | G4: 860 | H4: =UPPER(TRIM(A4)) -> PC-RCP-1200 | I4: =IF(OR(E4="",LEN(E4)<>7,MID(E4,5,1)<>"."),"HS code missing/format; ","")&IF(COUNTIF($H$2:$H$500,H4)>1,"Duplicate item; ","") | J4: =IF(I4="","OK","CHECK") -> OK
A5: PC-BOX-1812 | B5: Box culvert section 1.8 m x 1.2 m x 1.8 m | C5: Box Culvert | D5: EA | E5: 6810.91 | F5: 4200 | G5: 1950 | H5: =UPPER(TRIM(A5)) -> PC-BOX-1812 | I5: =IF(OR(E5="",LEN(E5)<>7,MID(E5,5,1)<>"."),"HS code missing/format; ","")&IF(COUNTIF($H$2:$H$500,H5)>1,"Duplicate item; ","") | J5: =IF(I5="","OK","CHECK") -> OK
A6: PC-MH-1050B | B6: Manhole base 1050 mm | C6: Manhole | D6: EA | E6: 6810.91 | F6: 980 | G6: 470 | H6: =UPPER(TRIM(A6)) -> PC-MH-1050B | I6: =IF(OR(E6="",LEN(E6)<>7,MID(E6,5,1)<>"."),"HS code missing/format; ","")&IF(COUNTIF($H$2:$H$500,H6)>1,"Duplicate item; ","") | J6: =IF(I6="","OK","CHECK") -> OK
A7: PC-MH-1200B | B7: Manhole base 1200 mm | C7: Manhole | D7: EA | E7: 6810.91 | F7: 1240 | G7: 600 | H7: =UPPER(TRIM(A7)) -> PC-MH-1200B | I7: =IF(OR(E7="",LEN(E7)<>7,MID(E7,5,1)<>"."),"HS code missing/format; ","")&IF(COUNTIF($H$2:$H$500,H7)>1,"Duplicate item; ","") | J7: =IF(I7="","OK","CHECK") -> OK
A8: PC-MH-1200R | B8: Manhole riser 1200 mm x 600 mm | C8: Manhole | D8: EA | E8: 6810.91 | F8: 520 | G8: 300 | H8: =UPPER(TRIM(A8)) -> PC-MH-1200R | I8: =IF(OR(E8="",LEN(E8)<>7,MID(E8,5,1)<>"."),"HS code missing/format; ","")&IF(COUNTIF($H$2:$H$500,H8)>1,"Duplicate item; ","") | J8: =IF(I8="","OK","CHECK") -> OK
A9: PC-CB-0600 | B9: Catch basin 600 mm x 600 mm | C9: Catch Basin | D9: EA | E9: 6810.91 | F9: 690 | G9: 170 | H9: =UPPER(TRIM(A9)) -> PC-CB-0600 | I9: =IF(OR(E9="",LEN(E9)<>7,MID(E9,5,1)<>"."),"HS code missing/format; ","")&IF(COUNTIF($H$2:$H$500,H9)>1,"Duplicate item; ","") | J9: =IF(I9="","OK","CHECK") -> OK
A10: PC-BAR-F38 | B10: F-shape traffic barrier 3.8 m | C10: Barrier | D10: EA | E10: 6810.99 | F10: 1450 | G10: 650 | H10: =UPPER(TRIM(A10)) -> PC-BAR-F38 | I10: =IF(OR(E10="",LEN(E10)<>7,MID(E10,5,1)<>"."),"HS code missing/format; ","")&IF(COUNTIF($H$2:$H$500,H10)>1,"Duplicate item; ","") | J10: =IF(I10="","OK","CHECK") -> OK
A11: PC-BAR-SS60 | B11: Single-slope traffic barrier 6.0 m | C11: Barrier | D11: EA | E11: 6810.99 | F11: 2350 | G11: 980 | H11: =UPPER(TRIM(A11)) -> PC-BAR-SS60 | I11: =IF(OR(E11="",LEN(E11)<>7,MID(E11,5,1)<>"."),"HS code missing/format; ","")&IF(COUNTIF($H$2:$H$500,H11)>1,"Duplicate item; ","") | J11: =IF(I11="","OK","CHECK") -> OK
A12: PC-HC-200 | B12: Hollow-core slab 200 mm (per m2) | C12: Slab | D12: M2 | E12: 6810.91 | F12: 118 | G12: 52 | H12: =UPPER(TRIM(A12)) -> PC-HC-200 | I12: =IF(OR(E12="",LEN(E12)<>7,MID(E12,5,1)<>"."),"HS code missing/format; ","")&IF(COUNTIF($H$2:$H$500,H12)>1,"Duplicate item; ","") | J12: =IF(I12="","OK","CHECK") -> OK
A13: PC-HC-250 | B13: Hollow-core slab 250 mm (per m2) | C13: Slab | D13: M2 | F13: 136 | G13: 60 | H13: =UPPER(TRIM(A13)) -> PC-HC-250 | I13: =IF(OR(E13="",LEN(E13)<>7,MID(E13,5,1)<>"."),"HS code missing/format; ","")&IF(COUNTIF($H$2:$H$500,H13)>1,"Duplicate item; ","") -> HS code missing/format; | J13: =IF(I13="","OK","CHECK") -> CHECK

Sheet Suppliers
A1: supplier_id | B1: supplier_name | C1: country | D1: currency | E1: lead_time_days | F1: lead_time_flag
A2: SUP-01 | B2: Prairie Cement Co. | C2: CA | D2: CAD | E2: 7 | F2: =IF(E2>Lead_Time_Flag,"Long lead time","")
A3: SUP-02 | B3: Great Plains Ash Inc. | C3: US | D3: USD | E3: 14 | F3: =IF(E3>Lead_Time_Flag,"Long lead time","")
A4: SUP-03 | B4: Red Valley Aggregates | C4: CA | D4: CAD | E4: 3 | F4: =IF(E4>Lead_Time_Flag,"Long lead time","")
A5: SUP-04 | B5: Midwest Admix Solutions | C5: US | D5: USD | E5: 10 | F5: =IF(E5>Lead_Time_Flag,"Long lead time","")
A6: SUP-05 | B6: Northern Rebar Mills | C6: CA | D6: CAD | E6: 10 | F6: =IF(E6>Lead_Time_Flag,"Long lead time","")
A7: SUP-06 | B7: Anatolia Steel Trading | C7: TR | D7: USD | E7: 60 | F7: =IF(E7>Lead_Time_Flag,"Long lead time","") -> Long lead time
A8: SUP-07 | B8: Lakeside Wire Products | C8: US | D8: USD | E8: 14 | F8: =IF(E8>Lead_Time_Flag,"Long lead time","")
A9: SUP-08 | B9: Hanbit Strand Co. | C9: KR | D9: USD | E9: 55 | F9: =IF(E9>Lead_Time_Flag,"Long lead time","") -> Long lead time
A10: SUP-09 | B10: Sierra Rubber Works | C10: MX | D10: USD | E10: 21 | F10: =IF(E10>Lead_Time_Flag,"Long lead time","")
A11: SUP-10 | B11: Rhein Lifting Systems | C11: DE | D11: EUR | E11: 45 | F11: =IF(E11>Lead_Time_Flag,"Long lead time","") -> Long lead time
A12: SUP-12 | B12: Westway Site Supply | C12: CA | D12: CAD | E12: 5 | F12: =IF(E12>Lead_Time_Flag,"Long lead time","")

Sheet Components
A1: comp_code | B1: description | C1: uom | D1: unit_cost | E1: currency | F1: supplier_id | G1: origin_country | H1: hs_code | I1: comp_key | J1: unit_cost_cad | K1: supplier_name | L1: key_count | M1: issues | N1: status
A2: CMT-GU | B2: Portland cement Type GU | C2: T | D2: 235 | E2: CAD | F2: SUP-01 | G2: CA | H2: 2523.29 | I2: =UPPER(TRIM(A2)) -> CMT-GU | J2: =IF(D2="","",IFERROR(D2*INDEX(FX_Rate,MATCH(E2,FX_Currency,0)),"NO FX RATE")) -> 235 | K2: =IFERROR(INDEX(Suppliers!$B$2:$B$500,MATCH(F2,Suppliers!$A$2:$A$500,0)),"NOT FOUND") -> Prairie Cement Co. | L2: =COUNTIF($I$2:$I$500,I2) -> 1 | M2: =IF(D2="","Missing cost; ","")&IF(G2="","Missing origin; ","")&IF(K2="NOT FOUND","Unknown supplier; ","")&IF(L2>1,"Duplicate code; ","")&IF(OR(H2="",LEN(H2)<>7,MID(H2,5,1)<>"."),"HS code format; ","")&IF(J2="NO FX RATE","No FX rate; ","") | N2: =IF(M2="","OK","CHECK") -> OK
A3: SCM-FA | B3: Fly ash Class F | C3: T | D3: 72 | E3: USD | F3: SUP-02 | G3: US | H3: 2621.90 | I3: =UPPER(TRIM(A3)) -> SCM-FA | J3: =IF(D3="","",IFERROR(D3*INDEX(FX_Rate,MATCH(E3,FX_Currency,0)),"NO FX RATE")) -> 98.64 | K3: =IFERROR(INDEX(Suppliers!$B$2:$B$500,MATCH(F3,Suppliers!$A$2:$A$500,0)),"NOT FOUND") -> Great Plains Ash Inc. | L3: =COUNTIF($I$2:$I$500,I3) -> 1 | M3: =IF(D3="","Missing cost; ","")&IF(G3="","Missing origin; ","")&IF(K3="NOT FOUND","Unknown supplier; ","")&IF(L3>1,"Duplicate code; ","")&IF(OR(H3="",LEN(H3)<>7,MID(H3,5,1)<>"."),"HS code format; ","")&IF(J3="NO FX RATE","No FX rate; ","") | N3: =IF(M3="","OK","CHECK") -> OK
A4: AGG-20 | B4: Coarse aggregate 20 mm | C4: T | D4: 28 | E4: CAD | F4: SUP-03 | G4: CA | H4: 2517.10 | I4: =UPPER(TRIM(A4)) -> AGG-20 | J4: =IF(D4="","",IFERROR(D4*INDEX(FX_Rate,MATCH(E4,FX_Currency,0)),"NO FX RATE")) -> 28 | K4: =IFERROR(INDEX(Suppliers!$B$2:$B$500,MATCH(F4,Suppliers!$A$2:$A$500,0)),"NOT FOUND") -> Red Valley Aggregates | L4: =COUNTIF($I$2:$I$500,I4) -> 1 | M4: =IF(D4="","Missing cost; ","")&IF(G4="","Missing origin; ","")&IF(K4="NOT FOUND","Unknown supplier; ","")&IF(L4>1,"Duplicate code; ","")&IF(OR(H4="",LEN(H4)<>7,MID(H4,5,1)<>"."),"HS code format; ","")&IF(J4="NO FX RATE","No FX rate; ","") | N4: =IF(M4="","OK","CHECK") -> OK
A5: AGG-SND | B5: Concrete sand | C5: T | D5: 24 | E5: CAD | F5: SUP-03 | G5: CA | H5: 2505.90 | I5: =UPPER(TRIM(A5)) -> AGG-SND | J5: =IF(D5="","",IFERROR(D5*INDEX(FX_Rate,MATCH(E5,FX_Currency,0)),"NO FX RATE")) -> 24 | K5: =IFERROR(INDEX(Suppliers!$B$2:$B$500,MATCH(F5,Suppliers!$A$2:$A$500,0)),"NOT FOUND") -> Red Valley Aggregates | L5: =COUNTIF($I$2:$I$500,I5) -> 1 | M5: =IF(D5="","Missing cost; ","")&IF(G5="","Missing origin; ","")&IF(K5="NOT FOUND","Unknown supplier; ","")&IF(L5>1,"Duplicate code; ","")&IF(OR(H5="",LEN(H5)<>7,MID(H5,5,1)<>"."),"HS code format; ","")&IF(J5="NO FX RATE","No FX rate; ","") | N5: =IF(M5="","OK","CHECK") -> OK
A6: ADM-SP | B6: Superplasticizer admixture | C6: L | D6: 3.1 | E6: USD | F6: SUP-04 | G6: US | H6: 3824.40 | I6: =UPPER(TRIM(A6)) -> ADM-SP | J6: =IF(D6="","",IFERROR(D6*INDEX(FX_Rate,MATCH(E6,FX_Currency,0)),"NO FX RATE")) -> 4.247 | K6: =IFERROR(INDEX(Suppliers!$B$2:$B$500,MATCH(F6,Suppliers!$A$2:$A$500,0)),"NOT FOUND") -> Midwest Admix Solutions | L6: =COUNTIF($I$2:$I$500,I6) -> 1 | M6: =IF(D6="","Missing cost; ","")&IF(G6="","Missing origin; ","")&IF(K6="NOT FOUND","Unknown supplier; ","")&IF(L6>1,"Duplicate code; ","")&IF(OR(H6="",LEN(H6)<>7,MID(H6,5,1)<>"."),"HS code format; ","")&IF(J6="NO FX RATE","No FX rate; ","") | N6: =IF(M6="","OK","CHECK") -> OK
A7: ADM-AE | B7: Air-entraining admixture | C7: L | D7: 2.4 | E7: USD | F7: SUP-04 | G7: US | H7: 382440 | I7: =UPPER(TRIM(A7)) -> ADM-AE | J7: =IF(D7="","",IFERROR(D7*INDEX(FX_Rate,MATCH(E7,FX_Currency,0)),"NO FX RATE")) -> 3.288 | K7: =IFERROR(INDEX(Suppliers!$B$2:$B$500,MATCH(F7,Suppliers!$A$2:$A$500,0)),"NOT FOUND") -> Midwest Admix Solutions | L7: =COUNTIF($I$2:$I$500,I7) -> 1 | M7: =IF(D7="","Missing cost; ","")&IF(G7="","Missing origin; ","")&IF(K7="NOT FOUND","Unknown supplier; ","")&IF(L7>1,"Duplicate code; ","")&IF(OR(H7="",LEN(H7)<>7,MID(H7,5,1)<>"."),"HS code format; ","")&IF(J7="NO FX RATE","No FX rate; ","") -> HS code format; | N7: =IF(M7="","OK","CHECK") -> CHECK
A8: RB-10M | B8: Rebar 10M | C8: KG | D8: 1.38 | E8: CAD | F8: SUP-05 | G8: CA | H8: 7214.20 | I8: =UPPER(TRIM(A8)) -> RB-10M | J8: =IF(D8="","",IFERROR(D8*INDEX(FX_Rate,MATCH(E8,FX_Currency,0)),"NO FX RATE")) -> 1.38 | K8: =IFERROR(INDEX(Suppliers!$B$2:$B$500,MATCH(F8,Suppliers!$A$2:$A$500,0)),"NOT FOUND") -> Northern Rebar Mills | L8: =COUNTIF($I$2:$I$500,I8) -> 1 | M8: =IF(D8="","Missing cost; ","")&IF(G8="","Missing origin; ","")&IF(K8="NOT FOUND","Unknown supplier; ","")&IF(L8>1,"Duplicate code; ","")&IF(OR(H8="",LEN(H8)<>7,MID(H8,5,1)<>"."),"HS code format; ","")&IF(J8="NO FX RATE","No FX rate; ","") | N8: =IF(M8="","OK","CHECK") -> OK
A9: RB-15M | B9: Rebar 15M | C9: KG | D9: 1.31 | E9: CAD | F9: SUP-05 | G9: CA | H9: 7214.20 | I9: =UPPER(TRIM(A9)) -> RB-15M | J9: =IF(D9="","",IFERROR(D9*INDEX(FX_Rate,MATCH(E9,FX_Currency,0)),"NO FX RATE")) -> 1.31 | K9: =IFERROR(INDEX(Suppliers!$B$2:$B$500,MATCH(F9,Suppliers!$A$2:$A$500,0)),"NOT FOUND") -> Northern Rebar Mills | L9: =COUNTIF($I$2:$I$500,I9) -> 2 | M9: =IF(D9="","Missing cost; ","")&IF(G9="","Missing origin; ","")&IF(K9="NOT FOUND","Unknown supplier; ","")&IF(L9>1,"Duplicate code; ","")&IF(OR(H9="",LEN(H9)<>7,MID(H9,5,1)<>"."),"HS code format; ","")&IF(J9="NO FX RATE","No FX rate; ","") -> Duplicate code; | N9: =IF(M9="","OK","CHECK") -> CHECK
A10: RB-20M | B10: Rebar 20M | C10: KG | D10: 0.93 | E10: USD | F10: SUP-06 | G10: TR | H10: 7214.20 | I10: =UPPER(TRIM(A10)) -> RB-20M | J10: =IF(D10="","",IFERROR(D10*INDEX(FX_Rate,MATCH(E10,FX_Currency,0)),"NO FX RATE")) -> 1.2741 | K10: =IFERROR(INDEX(Suppliers!$B$2:$B$500,MATCH(F10,Suppliers!$A$2:$A$500,0)),"NOT FOUND") -> Anatolia Steel Trading | L10: =COUNTIF($I$2:$I$500,I10) -> 1 | M10: =IF(D10="","Missing cost; ","")&IF(G10="","Missing origin; ","")&IF(K10="NOT FOUND","Unknown supplier; ","")&IF(L10>1,"Duplicate code; ","")&IF(OR(H10="",LEN(H10)<>7,MID(H10,5,1)<>"."),"HS code format; ","")&IF(J10="NO FX RATE","No FX rate; ","") | N10: =IF(M10="","OK","CHECK") -> OK
A11: WWM-152 | B11: Welded wire mesh 152x152 MW25.8 | C11: M2 | D11: 4.6 | E11: USD | F11: SUP-07 | G11: US | H11: 7314.20 | I11: =UPPER(TRIM(A11)) -> WWM-152 | J11: =IF(D11="","",IFERROR(D11*INDEX(FX_Rate,MATCH(E11,FX_Currency,0)),"NO FX RATE")) -> 6.302 | K11: =IFERROR(INDEX(Suppliers!$B$2:$B$500,MATCH(F11,Suppliers!$A$2:$A$500,0)),"NOT FOUND") -> Lakeside Wire Products | L11: =COUNTIF($I$2:$I$500,I11) -> 1 | M11: =IF(D11="","Missing cost; ","")&IF(G11="","Missing origin; ","")&IF(K11="NOT FOUND","Unknown supplier; ","")&IF(L11>1,"Duplicate code; ","")&IF(OR(H11="",LEN(H11)<>7,MID(H11,5,1)<>"."),"HS code format; ","")&IF(J11="NO FX RATE","No FX rate; ","") | N11: =IF(M11="","OK","CHECK") -> OK
A12: STR-127 | B12: Prestressing strand 12.7 mm | C12: KG | D12: 1.5 | E12: USD | F12: SUP-08 | G12: KR | H12: 7312.10 | I12: =UPPER(TRIM(A12)) -> STR-127 | J12: =IF(D12="","",IFERROR(D12*INDEX(FX_Rate,MATCH(E12,FX_Currency,0)),"NO FX RATE")) -> 2.055 | K12: =IFERROR(INDEX(Suppliers!$B$2:$B$500,MATCH(F12,Suppliers!$A$2:$A$500,0)),"NOT FOUND") -> Hanbit Strand Co. | L12: =COUNTIF($I$2:$I$500,I12) -> 1 | M12: =IF(D12="","Missing cost; ","")&IF(G12="","Missing origin; ","")&IF(K12="NOT FOUND","Unknown supplier; ","")&IF(L12>1,"Duplicate code; ","")&IF(OR(H12="",LEN(H12)<>7,MID(H12,5,1)<>"."),"HS code format; ","")&IF(J12="NO FX RATE","No FX rate; ","") | N12: =IF(M12="","OK","CHECK") -> OK
A13: GSK-0600 | B13: Rubber pipe gasket 600 mm | C13: EA | D13: 18.5 | E13: USD | F13: SUP-09 | G13: MX | H13: 4016.93 | I13: =UPPER(TRIM(A13)) -> GSK-0600 | J13: =IF(D13="","",IFERROR(D13*INDEX(FX_Rate,MATCH(E13,FX_Currency,0)),"NO FX RATE")) -> 25.345 | K13: =IFERROR(INDEX(Suppliers!$B$2:$B$500,MATCH(F13,Suppliers!$A$2:$A$500,0)),"NOT FOUND") -> Sierra Rubber Works | L13: =COUNTIF($I$2:$I$500,I13) -> 1 | M13: =IF(D13="","Missing cost; ","")&IF(G13="","Missing origin; ","")&IF(K13="NOT FOUND","Unknown supplier; ","")&IF(L13>1,"Duplicate code; ","")&IF(OR(H13="",LEN(H13)<>7,MID(H13,5,1)<>"."),"HS code format; ","")&IF(J13="NO FX RATE","No FX rate; ","") | N13: =IF(M13="","OK","CHECK") -> OK
A14: GSK-0900 | B14: Rubber pipe gasket 900 mm | C14: EA | D14: 26 | E14: USD | F14: SUP-09 | G14: MX | H14: 4016.93 | I14: =UPPER(TRIM(A14)) -> GSK-0900 | J14: =IF(D14="","",IFERROR(D14*INDEX(FX_Rate,MATCH(E14,FX_Currency,0)),"NO FX RATE")) -> 35.62 | K14: =IFERROR(INDEX(Suppliers!$B$2:$B$500,MATCH(F14,Suppliers!$A$2:$A$500,0)),"NOT FOUND") -> Sierra Rubber Works | L14: =COUNTIF($I$2:$I$500,I14) -> 1 | M14: =IF(D14="","Missing cost; ","")&IF(G14="","Missing origin; ","")&IF(K14="NOT FOUND","Unknown supplier; ","")&IF(L14>1,"Duplicate code; ","")&IF(OR(H14="",LEN(H14)<>7,MID(H14,5,1)<>"."),"HS code format; ","")&IF(J14="NO FX RATE","No FX rate; ","") | N14: =IF(M14="","OK","CHECK") -> OK
A15: GSK-1200 | B15: Rubber pipe gasket 1200 mm | C15: EA | D15: 34 | E15: USD | F15: SUP-09 | H15: 4016.93 | I15: =UPPER(TRIM(A15)) -> GSK-1200 | J15: =IF(D15="","",IFERROR(D15*INDEX(FX_Rate,MATCH(E15,FX_Currency,0)),"NO FX RATE")) -> 46.58 | K15: =IFERROR(INDEX(Suppliers!$B$2:$B$500,MATCH(F15,Suppliers!$A$2:$A$500,0)),"NOT FOUND") -> Sierra Rubber Works | L15: =COUNTIF($I$2:$I$500,I15) -> 1 | M15: =IF(D15="","Missing cost; ","")&IF(G15="","Missing origin; ","")&IF(K15="NOT FOUND","Unknown supplier; ","")&IF(L15>1,"Duplicate code; ","")&IF(OR(H15="",LEN(H15)<>7,MID(H15,5,1)<>"."),"HS code format; ","")&IF(J15="NO FX RATE","No FX rate; ","") -> Missing origin; | N15: =IF(M15="","OK","CHECK") -> CHECK
A16: LFT-ANC | B16: Lifting anchor 2.5 t | C16: EA | D16: 4.6 | E16: EUR | F16: SUP-10 | G16: DE | H16: 7326.90 | I16: =UPPER(TRIM(A16)) -> LFT-ANC | J16: =IF(D16="","",IFERROR(D16*INDEX(FX_Rate,MATCH(E16,FX_Currency,0)),"NO FX RATE")) -> 6.9 | K16: =IFERROR(INDEX(Suppliers!$B$2:$B$500,MATCH(F16,Suppliers!$A$2:$A$500,0)),"NOT FOUND") -> Rhein Lifting Systems | L16: =COUNTIF($I$2:$I$500,I16) -> 1 | M16: =IF(D16="","Missing cost; ","")&IF(G16="","Missing origin; ","")&IF(K16="NOT FOUND","Unknown supplier; ","")&IF(L16>1,"Duplicate code; ","")&IF(OR(H16="",LEN(H16)<>7,MID(H16,5,1)<>"."),"HS code format; ","")&IF(J16="NO FX RATE","No FX rate; ","") | N16: =IF(M16="","OK","CHECK") -> OK
A17: CST-FRM | B17: Catch basin frame and grate casting | C17: EA | D17: 210 | E17: CAD | F17: SUP-11 | G17: IN | H17: 7325.10 | I17: =UPPER(TRIM(A17)) -> CST-FRM | J17: =IF(D17="","",IFERROR(D17*INDEX(FX_Rate,MATCH(E17,FX_Currency,0)),"NO FX RATE")) -> 210 | K17: =IFERROR(INDEX(Suppliers!$B$2:$B$500,MATCH(F17,Suppliers!$A$2:$A$500,0)),"NOT FOUND") -> NOT FOUND | L17: =COUNTIF($I$2:$I$500,I17) -> 1 | M17: =IF(D17="","Missing cost; ","")&IF(G17="","Missing origin; ","")&IF(K17="NOT FOUND","Unknown supplier; ","")&IF(L17>1,"Duplicate code; ","")&IF(OR(H17="",LEN(H17)<>7,MID(H17,5,1)<>"."),"HS code format; ","")&IF(J17="NO FX RATE","No FX rate; ","") -> Unknown supplier; | N17: =IF(M17="","OK","CHECK") -> CHECK
A18: SEAL-BUT | B18: Butyl joint sealant | C18: M | E18: CAD | F18: SUP-12 | G18: CA | H18: 3214.10 | I18: =UPPER(TRIM(A18)) -> SEAL-BUT | J18: =IF(D18="","",IFERROR(D18*INDEX(FX_Rate,MATCH(E18,FX_Currency,0)),"NO FX RATE")) | K18: =IFERROR(INDEX(Suppliers!$B$2:$B$500,MATCH(F18,Suppliers!$A$2:$A$500,0)),"NOT FOUND") -> Westway Site Supply | L18: =COUNTIF($I$2:$I$500,I18) -> 1 | M18: =IF(D18="","Missing cost; ","")&IF(G18="","Missing origin; ","")&IF(K18="NOT FOUND","Unknown supplier; ","")&IF(L18>1,"Duplicate code; ","")&IF(OR(H18="",LEN(H18)<>7,MID(H18,5,1)<>"."),"HS code format; ","")&IF(J18="NO FX RATE","No FX rate; ","") -> Missing cost; | N18: =IF(M18="","OK","CHECK") -> CHECK
A19: FRM-OIL | B19: Form release agent | C19: L | D19: 1.15 | E19: CAD | F19: SUP-12 | G19: CA | H19: 2710.19 | I19: =UPPER(TRIM(A19)) -> FRM-OIL | J19: =IF(D19="","",IFERROR(D19*INDEX(FX_Rate,MATCH(E19,FX_Currency,0)),"NO FX RATE")) -> 1.15 | K19: =IFERROR(INDEX(Suppliers!$B$2:$B$500,MATCH(F19,Suppliers!$A$2:$A$500,0)),"NOT FOUND") -> Westway Site Supply | L19: =COUNTIF($I$2:$I$500,I19) -> 1 | M19: =IF(D19="","Missing cost; ","")&IF(G19="","Missing origin; ","")&IF(K19="NOT FOUND","Unknown supplier; ","")&IF(L19>1,"Duplicate code; ","")&IF(OR(H19="",LEN(H19)<>7,MID(H19,5,1)<>"."),"HS code format; ","")&IF(J19="NO FX RATE","No FX rate; ","") | N19: =IF(M19="","OK","CHECK") -> OK
A20: rb-15m | B20: Rebar 15M (old price) | C20: KG | D20: 1.29 | E20: CAD | F20: SUP-05 | G20: CA | H20: 7214.20 | I20: =UPPER(TRIM(A20)) -> RB-15M | J20: =IF(D20="","",IFERROR(D20*INDEX(FX_Rate,MATCH(E20,FX_Currency,0)),"NO FX RATE")) -> 1.29 | K20: =IFERROR(INDEX(Suppliers!$B$2:$B$500,MATCH(F20,Suppliers!$A$2:$A$500,0)),"NOT FOUND") -> Northern Rebar Mills | L20: =COUNTIF($I$2:$I$500,I20) -> 2 | M20: =IF(D20="","Missing cost; ","")&IF(G20="","Missing origin; ","")&IF(K20="NOT FOUND","Unknown supplier; ","")&IF(L20>1,"Duplicate code; ","")&IF(OR(H20="",LEN(H20)<>7,MID(H20,5,1)<>"."),"HS code format; ","")&IF(J20="NO FX RATE","No FX rate; ","") -> Duplicate code; | N20: =IF(M20="","OK","CHECK") -> CHECK

Sheet BOM
A1: parent_item | B1: line_no | C1: comp_code | D1: qty_per | E1: uom | F1: comp_key | G1: comp_description | H1: comp_uom | I1: conv_factor | J1: qty_in_comp_uom | K1: unit_cost_cad | L1: extended_cost_cad | M1: origin_country | N1: origin_group | O1: supplier_id | P1: units_sold_2025 | Q1: spend_2025_cad | R1: issues | S1: status
A2: PC-RCP-0600 | B2: 10 | C2: CMT-GU | D2: 0.133 | E2: T | F2: =UPPER(TRIM(C2)) -> CMT-GU | G2: =IFERROR(INDEX(Components!$B$2:$B$500,MATCH(F2,Components!$I$2:$I$500,0)),"NOT FOUND") -> Portland cement Type GU | H2: =IF(G2="NOT FOUND","",INDEX(Components!$C$2:$C$500,MATCH(F2,Components!$I$2:$I$500,0))) -> T | I2: =IF(G2="NOT FOUND","",IF(E2=H2,1,IFERROR(INDEX(Unit_Factor,MATCH(E2&">"&H2,Unit_Key,0)),"NO FACTOR"))) -> 1 | J2: =IF(ISNUMBER(I2),D2*I2,"") -> 0.133 | K2: =IF(G2="NOT FOUND","",INDEX(Components!$J$2:$J$500,MATCH(F2,Components!$I$2:$I$500,0))) -> 235 | L2: =IF(AND(ISNUMBER(J2),ISNUMBER(K2)),J2*K2,"") -> 31.255 | M2: =IF(G2="NOT FOUND","",IF(INDEX(Components!$G$2:$G$500,MATCH(F2,Components!$I$2:$I$500,0))="","UNKNOWN",INDEX(Components!$G$2:$G$500,MATCH(F2,Components!$I$2:$I$500,0)))) -> CA | N2: =IF(M2="","",IF(M2="UNKNOWN","Unknown",IF(M2=Home_Country,"Domestic","Imported"))) -> Domestic | O2: =IF(G2="NOT FOUND","",INDEX(Components!$F$2:$F$500,MATCH(F2,Components!$I$2:$I$500,0))) -> SUP-01 | P2: =SUMIFS(Sales!$G$2:$G$500,Sales!$I$2:$I$500,A2) -> 326 | Q2: =IF(ISNUMBER(L2),L2*P2,"") -> 10189.13 | R2: =IF(G2="NOT FOUND","Unknown component; ","")&IF(I2="NO FACTOR","No unit conversion; ","")&IF(AND(G2<>"NOT FOUND",K2=""),"Missing cost; ","")&IF(M2="UNKNOWN","Missing origin; ","") | S2: =IF(R2="","OK","CHECK") -> OK
A3: PC-RCP-0600 | B3: 20 | C3: SCM-FA | D3: 0.0266 | E3: T | F3: =UPPER(TRIM(C3)) -> SCM-FA | G3: =IFERROR(INDEX(Components!$B$2:$B$500,MATCH(F3,Components!$I$2:$I$500,0)),"NOT FOUND") -> Fly ash Class F | H3: =IF(G3="NOT FOUND","",INDEX(Components!$C$2:$C$500,MATCH(F3,Components!$I$2:$I$500,0))) -> T | I3: =IF(G3="NOT FOUND","",IF(E3=H3,1,IFERROR(INDEX(Unit_Factor,MATCH(E3&">"&H3,Unit_Key,0)),"NO FACTOR"))) -> 1 | J3: =IF(ISNUMBER(I3),D3*I3,"") -> 0.0266 | K3: =IF(G3="NOT FOUND","",INDEX(Components!$J$2:$J$500,MATCH(F3,Components!$I$2:$I$500,0))) -> 98.64 | L3: =IF(AND(ISNUMBER(J3),ISNUMBER(K3)),J3*K3,"") -> 2.623824 | M3: =IF(G3="NOT FOUND","",IF(INDEX(Components!$G$2:$G$500,MATCH(F3,Components!$I$2:$I$500,0))="","UNKNOWN",INDEX(Components!$G$2:$G$500,MATCH(F3,Components!$I$2:$I$500,0)))) -> US | N3: =IF(M3="","",IF(M3="UNKNOWN","Unknown",IF(M3=Home_Country,"Domestic","Imported"))) -> Imported | O3: =IF(G3="NOT FOUND","",INDEX(Components!$F$2:$F$500,MATCH(F3,Components!$I$2:$I$500,0))) -> SUP-02 | P3: =SUMIFS(Sales!$G$2:$G$500,Sales!$I$2:$I$500,A3) -> 326 | Q3: =IF(ISNUMBER(L3),L3*P3,"") -> 855.36662 | R3: =IF(G3="NOT FOUND","Unknown component; ","")&IF(I3="NO FACTOR","No unit conversion; ","")&IF(AND(G3<>"NOT FOUND",K3=""),"Missing cost; ","")&IF(M3="UNKNOWN","Missing origin; ","") | S3: =IF(R3="","OK","CHECK") -> OK
A4: PC-RCP-0600 | B4: 30 | C4: AGG-20 | D4: 0.399 | E4: T | F4: =UPPER(TRIM(C4)) -> AGG-20 | G4: =IFERROR(INDEX(Components!$B$2:$B$500,MATCH(F4,Components!$I$2:$I$500,0)),"NOT FOUND") -> Coarse aggregate 20 mm | H4: =IF(G4="NOT FOUND","",INDEX(Components!$C$2:$C$500,MATCH(F4,Components!$I$2:$I$500,0))) -> T | I4: =IF(G4="NOT FOUND","",IF(E4=H4,1,IFERROR(INDEX(Unit_Factor,MATCH(E4&">"&H4,Unit_Key,0)),"NO FACTOR"))) -> 1 | J4: =IF(ISNUMBER(I4),D4*I4,"") -> 0.399 | K4: =IF(G4="NOT FOUND","",INDEX(Components!$J$2:$J$500,MATCH(F4,Components!$I$2:$I$500,0))) -> 28 | L4: =IF(AND(ISNUMBER(J4),ISNUMBER(K4)),J4*K4,"") -> 11.172 | M4: =IF(G4="NOT FOUND","",IF(INDEX(Components!$G$2:$G$500,MATCH(F4,Components!$I$2:$I$500,0))="","UNKNOWN",INDEX(Components!$G$2:$G$500,MATCH(F4,Components!$I$2:$I$500,0)))) -> CA | N4: =IF(M4="","",IF(M4="UNKNOWN","Unknown",IF(M4=Home_Country,"Domestic","Imported"))) -> Domestic | O4: =IF(G4="NOT FOUND","",INDEX(Components!$F$2:$F$500,MATCH(F4,Components!$I$2:$I$500,0))) -> SUP-03 | P4: =SUMIFS(Sales!$G$2:$G$500,Sales!$I$2:$I$500,A4) -> 326 | Q4: =IF(ISNUMBER(L4),L4*P4,"") -> 3642.072 | R4: =IF(G4="NOT FOUND","Unknown component; ","")&IF(I4="NO FACTOR","No unit conversion; ","")&IF(AND(G4<>"NOT FOUND",K4=""),"Missing cost; ","")&IF(M4="UNKNOWN","Missing origin; ","") | S4: =IF(R4="","OK","CHECK") -> OK
A5: PC-RCP-0600 | B5: 40 | C5: AGG-SND | D5: 0.285 | E5: T | F5: =UPPER(TRIM(C5)) -> AGG-SND | G5: =IFERROR(INDEX(Components!$B$2:$B$500,MATCH(F5,Components!$I$2:$I$500,0)),"NOT FOUND") -> Concrete sand | H5: =IF(G5="NOT FOUND","",INDEX(Components!$C$2:$C$500,MATCH(F5,Components!$I$2:$I$500,0))) -> T | I5: =IF(G5="NOT FOUND","",IF(E5=H5,1,IFERROR(INDEX(Unit_Factor,MATCH(E5&">"&H5,Unit_Key,0)),"NO FACTOR"))) -> 1 | J5: =IF(ISNUMBER(I5),D5*I5,"") -> 0.285 | K5: =IF(G5="NOT FOUND","",INDEX(Components!$J$2:$J$500,MATCH(F5,Components!$I$2:$I$500,0))) -> 24 | L5: =IF(AND(ISNUMBER(J5),ISNUMBER(K5)),J5*K5,"") -> 6.84 | M5: =IF(G5="NOT FOUND","",IF(INDEX(Components!$G$2:$G$500,MATCH(F5,Components!$I$2:$I$500,0))="","UNKNOWN",INDEX(Components!$G$2:$G$500,MATCH(F5,Components!$I$2:$I$500,0)))) -> CA | N5: =IF(M5="","",IF(M5="UNKNOWN","Unknown",IF(M5=Home_Country,"Domestic","Imported"))) -> Domestic | O5: =IF(G5="NOT FOUND","",INDEX(Components!$F$2:$F$500,MATCH(F5,Components!$I$2:$I$500,0))) -> SUP-03 | P5: =SUMIFS(Sales!$G$2:$G$500,Sales!$I$2:$I$500,A5) -> 326 | Q5: =IF(ISNUMBER(L5),L5*P5,"") -> 2229.84 | R5: =IF(G5="NOT FOUND","Unknown component; ","")&IF(I5="NO FACTOR","No unit conversion; ","")&IF(AND(G5<>"NOT FOUND",K5=""),"Missing cost; ","")&IF(M5="UNKNOWN","Missing origin; ","") | S5: =IF(R5="","OK","CHECK") -> OK
A6: PC-RCP-0600 | B6: 50 | C6: ADM-SP | D6: 0.76 | E6: L | F6: =UPPER(TRIM(C6)) -> ADM-SP | G6: =IFERROR(INDEX(Components!$B$2:$B$500,MATCH(F6,Components!$I$2:$I$500,0)),"NOT FOUND") -> Superplasticizer admixture | H6: =IF(G6="NOT FOUND","",INDEX(Components!$C$2:$C$500,MATCH(F6,Components!$I$2:$I$500,0))) -> L | I6: =IF(G6="NOT FOUND","",IF(E6=H6,1,IFERROR(INDEX(Unit_Factor,MATCH(E6&">"&H6,Unit_Key,0)),"NO FACTOR"))) -> 1 | J6: =IF(ISNUMBER(I6),D6*I6,"") -> 0.76 | K6: =IF(G6="NOT FOUND","",INDEX(Components!$J$2:$J$500,MATCH(F6,Components!$I$2:$I$500,0))) -> 4.247 | L6: =IF(AND(ISNUMBER(J6),ISNUMBER(K6)),J6*K6,"") -> 3.22772 | M6: =IF(G6="NOT FOUND","",IF(INDEX(Components!$G$2:$G$500,MATCH(F6,Components!$I$2:$I$500,0))="","UNKNOWN",INDEX(Components!$G$2:$G$500,MATCH(F6,Components!$I$2:$I$500,0)))) -> US | N6: =IF(M6="","",IF(M6="UNKNOWN","Unknown",IF(M6=Home_Country,"Domestic","Imported"))) -> Imported | O6: =IF(G6="NOT FOUND","",INDEX(Components!$F$2:$F$500,MATCH(F6,Components!$I$2:$I$500,0))) -> SUP-04 | P6: =SUMIFS(Sales!$G$2:$G$500,Sales!$I$2:$I$500,A6) -> 326 | Q6: =IF(ISNUMBER(L6),L6*P6,"") -> 1052.2367 | R6: =IF(G6="NOT FOUND","Unknown component; ","")&IF(I6="NO FACTOR","No unit conversion; ","")&IF(AND(G6<>"NOT FOUND",K6=""),"Missing cost; ","")&IF(M6="UNKNOWN","Missing origin; ","") | S6: =IF(R6="","OK","CHECK") -> OK
A7: PC-RCP-0600 | B7: 60 | C7: ADM-AE | D7: 0.152 | E7: L | F7: =UPPER(TRIM(C7)) -> ADM-AE | G7: =IFERROR(INDEX(Components!$B$2:$B$500,MATCH(F7,Components!$I$2:$I$500,0)),"NOT FOUND") -> Air-entraining admixture | H7: =IF(G7="NOT FOUND","",INDEX(Components!$C$2:$C$500,MATCH(F7,Components!$I$2:$I$500,0))) -> L | I7: =IF(G7="NOT FOUND","",IF(E7=H7,1,IFERROR(INDEX(Unit_Factor,MATCH(E7&">"&H7,Unit_Key,0)),"NO FACTOR"))) -> 1 | J7: =IF(ISNUMBER(I7),D7*I7,"") -> 0.152 | K7: =IF(G7="NOT FOUND","",INDEX(Components!$J$2:$J$500,MATCH(F7,Components!$I$2:$I$500,0))) -> 3.288 | L7: =IF(AND(ISNUMBER(J7),ISNUMBER(K7)),J7*K7,"") -> 0.499776 | M7: =IF(G7="NOT FOUND","",IF(INDEX(Components!$G$2:$G$500,MATCH(F7,Components!$I$2:$I$500,0))="","UNKNOWN",INDEX(Components!$G$2:$G$500,MATCH(F7,Components!$I$2:$I$500,0)))) -> US | N7: =IF(M7="","",IF(M7="UNKNOWN","Unknown",IF(M7=Home_Country,"Domestic","Imported"))) -> Imported | O7: =IF(G7="NOT FOUND","",INDEX(Components!$F$2:$F$500,MATCH(F7,Components!$I$2:$I$500,0))) -> SUP-04 | P7: =SUMIFS(Sales!$G$2:$G$500,Sales!$I$2:$I$500,A7) -> 326 | Q7: =IF(ISNUMBER(L7),L7*P7,"") -> 162.92698 | R7: =IF(G7="NOT FOUND","Unknown component; ","")&IF(I7="NO FACTOR","No unit conversion; ","")&IF(AND(G7<>"NOT FOUND",K7=""),"Missing cost; ","")&IF(M7="UNKNOWN","Missing origin; ","") | S7: =IF(R7="","OK","CHECK") -> OK
A8: PC-RCP-0600 | B8: 70 | C8: RB-10M | D8: 28 | E8: KG | F8: =UPPER(TRIM(C8)) -> RB-10M | G8: =IFERROR(INDEX(Components!$B$2:$B$500,MATCH(F8,Components!$I$2:$I$500,0)),"NOT FOUND") -> Rebar 10M | H8: =IF(G8="NOT FOUND","",INDEX(Components!$C$2:$C$500,MATCH(F8,Components!$I$2:$I$500,0))) -> KG | I8: =IF(G8="NOT FOUND","",IF(E8=H8,1,IFERROR(INDEX(Unit_Factor,MATCH(E8&">"&H8,Unit_Key,0)),"NO FACTOR"))) -> 1 | J8: =IF(ISNUMBER(I8),D8*I8,"") -> 28 | K8: =IF(G8="NOT FOUND","",INDEX(Components!$J$2:$J$500,MATCH(F8,Components!$I$2:$I$500,0))) -> 1.38 | L8: =IF(AND(ISNUMBER(J8),ISNUMBER(K8)),J8*K8,"") -> 38.64 | M8: =IF(G8="NOT FOUND","",IF(INDEX(Components!$G$2:$G$500,MATCH(F8,Components!$I$2:$I$500,0))="","UNKNOWN",INDEX(Components!$G$2:$G$500,MATCH(F8,Components!$I$2:$I$500,0)))) -> CA | N8: =IF(M8="","",IF(M8="UNKNOWN","Unknown",IF(M8=Home_Country,"Domestic","Imported"))) -> Domestic | O8: =IF(G8="NOT FOUND","",INDEX(Components!$F$2:$F$500,MATCH(F8,Components!$I$2:$I$500,0))) -> SUP-05 | P8: =SUMIFS(Sales!$G$2:$G$500,Sales!$I$2:$I$500,A8) -> 326 | Q8: =IF(ISNUMBER(L8),L8*P8,"") -> 12596.64 | R8: =IF(G8="NOT FOUND","Unknown component; ","")&IF(I8="NO FACTOR","No unit conversion; ","")&IF(AND(G8<>"NOT FOUND",K8=""),"Missing cost; ","")&IF(M8="UNKNOWN","Missing origin; ","") | S8: =IF(R8="","OK","CHECK") -> OK
A9: PC-RCP-0600 | B9: 80 | C9: GSK-0600 | D9: 1 | E9: EA | F9: =UPPER(TRIM(C9)) -> GSK-0600 | G9: =IFERROR(INDEX(Components!$B$2:$B$500,MATCH(F9,Components!$I$2:$I$500,0)),"NOT FOUND") -> Rubber pipe gasket 600 mm | H9: =IF(G9="NOT FOUND","",INDEX(Components!$C$2:$C$500,MATCH(F9,Components!$I$2:$I$500,0))) -> EA | I9: =IF(G9="NOT FOUND","",IF(E9=H9,1,IFERROR(INDEX(Unit_Factor,MATCH(E9&">"&H9,Unit_Key,0)),"NO FACTOR"))) -> 1 | J9: =IF(ISNUMBER(I9),D9*I9,"") -> 1 | K9: =IF(G9="NOT FOUND","",INDEX(Components!$J$2:$J$500,MATCH(F9,Components!$I$2:$I$500,0))) -> 25.345 | L9: =IF(AND(ISNUMBER(J9),ISNUMBER(K9)),J9*K9,"") -> 25.345 | M9: =IF(G9="NOT FOUND","",IF(INDEX(Components!$G$2:$G$500,MATCH(F9,Components!$I$2:$I$500,0))="","UNKNOWN",INDEX(Components!$G$2:$G$500,MATCH(F9,Components!$I$2:$I$500,0)))) -> MX | N9: =IF(M9="","",IF(M9="UNKNOWN","Unknown",IF(M9=Home_Country,"Domestic","Imported"))) -> Imported | O9: =IF(G9="NOT FOUND","",INDEX(Components!$F$2:$F$500,MATCH(F9,Components!$I$2:$I$500,0))) -> SUP-09 | P9: =SUMIFS(Sales!$G$2:$G$500,Sales!$I$2:$I$500,A9) -> 326 | Q9: =IF(ISNUMBER(L9),L9*P9,"") -> 8262.47 | R9: =IF(G9="NOT FOUND","Unknown component; ","")&IF(I9="NO FACTOR","No unit conversion; ","")&IF(AND(G9<>"NOT FOUND",K9=""),"Missing cost; ","")&IF(M9="UNKNOWN","Missing origin; ","") | S9: =IF(R9="","OK","CHECK") -> OK
A10: PC-RCP-0600 | B10: 90 | C10: FRM-OIL | D10: 0.3 | E10: L | F10: =UPPER(TRIM(C10)) -> FRM-OIL | G10: =IFERROR(INDEX(Components!$B$2:$B$500,MATCH(F10,Components!$I$2:$I$500,0)),"NOT FOUND") -> Form release agent | H10: =IF(G10="NOT FOUND","",INDEX(Components!$C$2:$C$500,MATCH(F10,Components!$I$2:$I$500,0))) -> L | I10: =IF(G10="NOT FOUND","",IF(E10=H10,1,IFERROR(INDEX(Unit_Factor,MATCH(E10&">"&H10,Unit_Key,0)),"NO FACTOR"))) -> 1 | J10: =IF(ISNUMBER(I10),D10*I10,"") -> 0.3 | K10: =IF(G10="NOT FOUND","",INDEX(Components!$J$2:$J$500,MATCH(F10,Components!$I$2:$I$500,0))) -> 1.15 | L10: =IF(AND(ISNUMBER(J10),ISNUMBER(K10)),J10*K10,"") -> 0.345 | M10: =IF(G10="NOT FOUND","",IF(INDEX(Components!$G$2:$G$500,MATCH(F10,Components!$I$2:$I$500,0))="","UNKNOWN",INDEX(Components!$G$2:$G$500,MATCH(F10,Components!$I$2:$I$500,0)))) -> CA | N10: =IF(M10="","",IF(M10="UNKNOWN","Unknown",IF(M10=Home_Country,"Domestic","Imported"))) -> Domestic | O10: =IF(G10="NOT FOUND","",INDEX(Components!$F$2:$F$500,MATCH(F10,Components!$I$2:$I$500,0))) -> SUP-12 | P10: =SUMIFS(Sales!$G$2:$G$500,Sales!$I$2:$I$500,A10) -> 326 | Q10: =IF(ISNUMBER(L10),L10*P10,"") -> 112.47 | R10: =IF(G10="NOT FOUND","Unknown component; ","")&IF(I10="NO FACTOR","No unit conversion; ","")&IF(AND(G10<>"NOT FOUND",K10=""),"Missing cost; ","")&IF(M10="UNKNOWN","Missing origin; ","") | S10: =IF(R10="","OK","CHECK") -> OK
A11: PC-RCP-0900 | B11: 10 | C11: CMT-GU | D11: 0.245 | E11: T | F11: =UPPER(TRIM(C11)) -> CMT-GU | G11: =IFERROR(INDEX(Components!$B$2:$B$500,MATCH(F11,Components!$I$2:$I$500,0)),"NOT FOUND") -> Portland cement Type GU | H11: =IF(G11="NOT FOUND","",INDEX(Components!$C$2:$C$500,MATCH(F11,Components!$I$2:$I$500,0))) -> T | I11: =IF(G11="NOT FOUND","",IF(E11=H11,1,IFERROR(INDEX(Unit_Factor,MATCH(E11&">"&H11,Unit_Key,0)),"NO FACTOR"))) -> 1 | J11: =IF(ISNUMBER(I11),D11*I11,"") -> 0.245 | K11: =IF(G11="NOT FOUND","",INDEX(Components!$J$2:$J$500,MATCH(F11,Components!$I$2:$I$500,0))) -> 235 | L11: =IF(AND(ISNUMBER(J11),ISNUMBER(K11)),J11*K11,"") -> 57.575 | M11: =IF(G11="NOT FOUND","",IF(INDEX(Components!$G$2:$G$500,MATCH(F11,Components!$I$2:$I$500,0))="","UNKNOWN",INDEX(Components!$G$2:$G$500,MATCH(F11,Components!$I$2:$I$500,0)))) -> CA | N11: =IF(M11="","",IF(M11="UNKNOWN","Unknown",IF(M11=Home_Country,"Domestic","Imported"))) -> Domestic | O11: =IF(G11="NOT FOUND","",INDEX(Components!$F$2:$F$500,MATCH(F11,Components!$I$2:$I$500,0))) -> SUP-01 | P11: =SUMIFS(Sales!$G$2:$G$500,Sales!$I$2:$I$500,A11) -> 366 | Q11: =IF(ISNUMBER(L11),L11*P11,"") -> 21072.45 | R11: =IF(G11="NOT FOUND","Unknown component; ","")&IF(I11="NO FACTOR","No unit conversion; ","")&IF(AND(G11<>"NOT FOUND",K11=""),"Missing cost; ","")&IF(M11="UNKNOWN","Missing origin; ","") | S11: =IF(R11="","OK","CHECK") -> OK
A12: PC-RCP-0900 | B12: 20 | C12: SCM-FA | D12: 0.049 | E12: T | F12: =UPPER(TRIM(C12)) -> SCM-FA | G12: =IFERROR(INDEX(Components!$B$2:$B$500,MATCH(F12,Components!$I$2:$I$500,0)),"NOT FOUND") -> Fly ash Class F | H12: =IF(G12="NOT FOUND","",INDEX(Components!$C$2:$C$500,MATCH(F12,Components!$I$2:$I$500,0))) -> T | I12: =IF(G12="NOT FOUND","",IF(E12=H12,1,IFERROR(INDEX(Unit_Factor,MATCH(E12&">"&H12,Unit_Key,0)),"NO FACTOR"))) -> 1 | J12: =IF(ISNUMBER(I12),D12*I12,"") -> 0.049 | K12: =IF(G12="NOT FOUND","",INDEX(Components!$J$2:$J$500,MATCH(F12,Components!$I$2:$I$500,0))) -> 98.64 | L12: =IF(AND(ISNUMBER(J12),ISNUMBER(K12)),J12*K12,"") -> 4.83336 | M12: =IF(G12="NOT FOUND","",IF(INDEX(Components!$G$2:$G$500,MATCH(F12,Components!$I$2:$I$500,0))="","UNKNOWN",INDEX(Components!$G$2:$G$500,MATCH(F12,Components!$I$2:$I$500,0)))) -> US | N12: =IF(M12="","",IF(M12="UNKNOWN","Unknown",IF(M12=Home_Country,"Domestic","Imported"))) -> Imported | O12: =IF(G12="NOT FOUND","",INDEX(Components!$F$2:$F$500,MATCH(F12,Components!$I$2:$I$500,0))) -> SUP-02 | P12: =SUMIFS(Sales!$G$2:$G$500,Sales!$I$2:$I$500,A12) -> 366 | Q12: =IF(ISNUMBER(L12),L12*P12,"") -> 1769.0098 | R12: =IF(G12="NOT FOUND","Unknown component; ","")&IF(I12="NO FACTOR","No unit conversion; ","")&IF(AND(G12<>"NOT FOUND",K12=""),"Missing cost; ","")&IF(M12="UNKNOWN","Missing origin; ","") | S12: =IF(R12="","OK","CHECK") -> OK
A13: PC-RCP-0900 | B13: 30 | C13: AGG-20 | D13: 0.735 | E13: T | F13: =UPPER(TRIM(C13)) -> AGG-20 | G13: =IFERROR(INDEX(Components!$B$2:$B$500,MATCH(F13,Components!$I$2:$I$500,0)),"NOT FOUND") -> Coarse aggregate 20 mm | H13: =IF(G13="NOT FOUND","",INDEX(Components!$C$2:$C$500,MATCH(F13,Components!$I$2:$I$500,0))) -> T | I13: =IF(G13="NOT FOUND","",IF(E13=H13,1,IFERROR(INDEX(Unit_Factor,MATCH(E13&">"&H13,Unit_Key,0)),"NO FACTOR"))) -> 1 | J13: =IF(ISNUMBER(I13),D13*I13,"") -> 0.735 | K13: =IF(G13="NOT FOUND","",INDEX(Components!$J$2:$J$500,MATCH(F13,Components!$I$2:$I$500,0))) -> 28 | L13: =IF(AND(ISNUMBER(J13),ISNUMBER(K13)),J13*K13,"") -> 20.58 | M13: =IF(G13="NOT FOUND","",IF(INDEX(Components!$G$2:$G$500,MATCH(F13,Components!$I$2:$I$500,0))="","UNKNOWN",INDEX(Components!$G$2:$G$500,MATCH(F13,Components!$I$2:$I$500,0)))) -> CA | N13: =IF(M13="","",IF(M13="UNKNOWN","Unknown",IF(M13=Home_Country,"Domestic","Imported"))) -> Domestic | O13: =IF(G13="NOT FOUND","",INDEX(Components!$F$2:$F$500,MATCH(F13,Components!$I$2:$I$500,0))) -> SUP-03 | P13: =SUMIFS(Sales!$G$2:$G$500,Sales!$I$2:$I$500,A13) -> 366 | Q13: =IF(ISNUMBER(L13),L13*P13,"") -> 7532.28 | R13: =IF(G13="NOT FOUND","Unknown component; ","")&IF(I13="NO FACTOR","No unit conversion; ","")&IF(AND(G13<>"NOT FOUND",K13=""),"Missing cost; ","")&IF(M13="UNKNOWN","Missing origin; ","") | S13: =IF(R13="","OK","CHECK") -> OK
... A112: PC-HC-250 | B112: 80 | C112: FRM-OIL | D112: 0.06 | E112: L | F112: =UPPER(TRIM(C112)) -> FRM-OIL | G112: =IFERROR(INDEX(Components!$B$2:$B$500,MATCH(F112,Components!$I$2:$I$500,0)),"NOT FOUND") -> Form release agent | H112: =IF(G112="NOT FOUND","",INDEX(Components!$C$2:$C$500,MATCH(F112,Components!$I$2:$I$500,0))) -> L | I112: =IF(G112="NOT FOUND","",IF(E112=H112,1,IFERROR(INDEX(Unit_Factor,MATCH(E112&">"&H112,Unit_Key,0)),"NO FACTOR"))) -> 1 | J112: =IF(ISNUMBER(I112),D112*I112,"") -> 0.06 | K112: =IF(G112="NOT FOUND","",INDEX(Components!$J$2:$J$500,MATCH(F112,Components!$I$2:$I$500,0))) -> 1.15 | L112: =IF(AND(ISNUMBER(J112),ISNUMBER(K112)),J112*K112,"") -> 0.069 | M112: =IF(G112="NOT FOUND","",IF(INDEX(Components!$G$2:$G$500,MATCH(F112,Components!$I$2:$I$500,0))="","UNKNOWN",INDEX(Components!$G$2:$G$500,MATCH(F112,Components!$I$2:$I$500,0)))) -> CA | N112: =IF(M112="","",IF(M112="UNKNOWN","Unknown",IF(M112=Home_Country,"Domestic","Imported"))) -> Domestic | O112: =IF(G112="NOT FOUND","",INDEX(Components!$F$2:$F$500,MATCH(F112,Components!$I$2:$I$500,0))) -> SUP-12 | P112: =SUMIFS(Sales!$G$2:$G$500,Sales!$I$2:$I$500,A112) -> 3012 | Q112: =IF(ISNUMBER(L112),L112*P112,"") -> 207.828 | R112: =IF(G112="NOT FOUND","Unknown component; ","")&IF(I112="NO FACTOR","No unit conversion; ","")&IF(AND(G112<>"NOT FOUND",K112=""),"Missing cost; ","")&IF(M112="UNKNOWN","Missing origin; ","") | S112: =IF(R112="","OK","CHECK") -> OK

Sheet Sales
A1: invoice_no | B1: invoice_date | C1: customer_id | D1: ship_to_region | E1: ship_to_country | F1: item_no | G1: qty | H1: unit_price_cad | I1: item_key | J1: category | K1: list_price_cad | L1: revenue_cad | M1: priced_qty | N1: discount_vs_list | O1: unit_cost_cad | P1: cost_of_sales_cad | Q1: issues | R1: status
A2: INV-25101 | B2: 45664 | C2: CUST-006 | D2: AB | E2: CA | F2: PC-RCP-0900 | G2: 15 | H2: 1083.73 | I2: =UPPER(TRIM(F2)) -> PC-RCP-0900 | J2: =IFERROR(INDEX(Items!$C$2:$C$500,MATCH(I2,Items!$H$2:$H$500,0)),"UNKNOWN") -> Pipe | K2: =IF(J2="UNKNOWN","",INDEX(Items!$F$2:$F$500,MATCH(I2,Items!$H$2:$H$500,0))) -> 1150 | L2: =IF(ISNUMBER(H2),G2*H2,"") -> 16255.95 | M2: =IF(ISNUMBER(H2),G2,0) -> 15 | N2: =IF(AND(ISNUMBER(H2),ISNUMBER(K2)),1-H2/K2,"") -> 0.057626087 | O2: =IF(J2="UNKNOWN","",INDEX(Cost_Rollup!$F$5:$F$16,MATCH(I2,Cost_Rollup!$A$5:$A$16,0))) -> 750.43373 | P2: =IF(AND(ISNUMBER(L2),ISNUMBER(O2)),G2*O2,"") -> 11256.506 | Q2: =IF(H2="","Missing price; ","")&IF(J2="UNKNOWN","Unknown item; ","")&IF(AND(ISNUMBER(N2),N2>Discount_Threshold),"Discount above limit; ","") | R2: =IF(Q2="","OK","CHECK") -> OK
A3: INV-25244 | B3: 45664 | C3: CUST-002 | D3: AB | E3: CA | F3: PC-RCP-0900 | G3: 28 | H3: 1090.02 | I3: =UPPER(TRIM(F3)) -> PC-RCP-0900 | J3: =IFERROR(INDEX(Items!$C$2:$C$500,MATCH(I3,Items!$H$2:$H$500,0)),"UNKNOWN") -> Pipe | K3: =IF(J3="UNKNOWN","",INDEX(Items!$F$2:$F$500,MATCH(I3,Items!$H$2:$H$500,0))) -> 1150 | L3: =IF(ISNUMBER(H3),G3*H3,"") -> 30520.56 | M3: =IF(ISNUMBER(H3),G3,0) -> 28 | N3: =IF(AND(ISNUMBER(H3),ISNUMBER(K3)),1-H3/K3,"") -> 0.052156522 | O3: =IF(J3="UNKNOWN","",INDEX(Cost_Rollup!$F$5:$F$16,MATCH(I3,Cost_Rollup!$A$5:$A$16,0))) -> 750.43373 | P3: =IF(AND(ISNUMBER(L3),ISNUMBER(O3)),G3*O3,"") -> 21012.144 | Q3: =IF(H3="","Missing price; ","")&IF(J3="UNKNOWN","Unknown item; ","")&IF(AND(ISNUMBER(N3),N3>Discount_Threshold),"Discount above limit; ","") | R3: =IF(Q3="","OK","CHECK") -> OK
A4: INV-25088 | B4: 45665 | C4: CUST-006 | D4: AB | E4: CA | F4: PC-BAR-F38 | G4: 31 | H4: 1466.46 | I4: =UPPER(TRIM(F4)) -> PC-BAR-F38 | J4: =IFERROR(INDEX(Items!$C$2:$C$500,MATCH(I4,Items!$H$2:$H$500,0)),"UNKNOWN") -> Barrier | K4: =IF(J4="UNKNOWN","",INDEX(Items!$F$2:$F$500,MATCH(I4,Items!$H$2:$H$500,0))) -> 1450 | L4: =IF(ISNUMBER(H4),G4*H4,"") -> 45460.26 | M4: =IF(ISNUMBER(H4),G4,0) -> 31 | N4: =IF(AND(ISNUMBER(H4),ISNUMBER(K4)),1-H4/K4,"") -> -0.011351724 | O4: =IF(J4="UNKNOWN","",INDEX(Cost_Rollup!$F$5:$F$16,MATCH(I4,Cost_Rollup!$A$5:$A$16,0))) -> 978.66328 | P4: =IF(AND(ISNUMBER(L4),ISNUMBER(O4)),G4*O4,"") -> 30338.562 | Q4: =IF(H4="","Missing price; ","")&IF(J4="UNKNOWN","Unknown item; ","")&IF(AND(ISNUMBER(N4),N4>Discount_Threshold),"Discount above limit; ","") | R4: =IF(Q4="","OK","CHECK") -> OK
A5: INV-25021 | B5: 45667 | C5: CUST-001 | D5: AB | E5: CA | F5: PC-RCP-1200 | G5: 24 | H5: 1934.39 | I5: =UPPER(TRIM(F5)) -> PC-RCP-1200 | J5: =IFERROR(INDEX(Items!$C$2:$C$500,MATCH(I5,Items!$H$2:$H$500,0)),"UNKNOWN") -> Pipe | K5: =IF(J5="UNKNOWN","",INDEX(Items!$F$2:$F$500,MATCH(I5,Items!$H$2:$H$500,0))) -> 1890 | L5: =IF(ISNUMBER(H5),G5*H5,"") -> 46425.36 | M5: =IF(ISNUMBER(H5),G5,0) -> 24 | N5: =IF(AND(ISNUMBER(H5),ISNUMBER(K5)),1-H5/K5,"") -> -0.023486772 | O5: =IF(J5="UNKNOWN","",INDEX(Cost_Rollup!$F$5:$F$16,MATCH(I5,Cost_Rollup!$A$5:$A$16,0))) -> 1206.4054 | P5: =IF(AND(ISNUMBER(L5),ISNUMBER(O5)),G5*O5,"") -> 28953.73 | Q5: =IF(H5="","Missing price; ","")&IF(J5="UNKNOWN","Unknown item; ","")&IF(AND(ISNUMBER(N5),N5>Discount_Threshold),"Discount above limit; ","") | R5: =IF(Q5="","OK","CHECK") -> OK
A6: INV-25082 | B6: 45668 | C6: CUST-004 | D6: BC | E6: CA | F6: PC-CB-0600 | G6: 2 | H6: 714.72 | I6: =UPPER(TRIM(F6)) -> PC-CB-0600 | J6: =IFERROR(INDEX(Items!$C$2:$C$500,MATCH(I6,Items!$H$2:$H$500,0)),"UNKNOWN") -> Catch Basin | K6: =IF(J6="UNKNOWN","",INDEX(Items!$F$2:$F$500,MATCH(I6,Items!$H$2:$H$500,0))) -> 690 | L6: =IF(ISNUMBER(H6),G6*H6,"") -> 1429.44 | M6: =IF(ISNUMBER(H6),G6,0) -> 2 | N6: =IF(AND(ISNUMBER(H6),ISNUMBER(K6)),1-H6/K6,"") -> -0.035826087 | O6: =IF(J6="UNKNOWN","",INDEX(Cost_Rollup!$F$5:$F$16,MATCH(I6,Cost_Rollup!$A$5:$A$16,0))) -> 471.0488 | P6: =IF(AND(ISNUMBER(L6),ISNUMBER(O6)),G6*O6,"") -> 942.0976 | Q6: =IF(H6="","Missing price; ","")&IF(J6="UNKNOWN","Unknown item; ","")&IF(AND(ISNUMBER(N6),N6>Discount_Threshold),"Discount above limit; ","") | R6: =IF(Q6="","OK","CHECK") -> OK
A7: INV-25122 | B7: 45668 | C7: CUST-005 | D7: MB | E7: CA | F7: PC-BAR-F38 | G7: 21 | H7: 1331.51 | I7: =UPPER(TRIM(F7)) -> PC-BAR-F38 | J7: =IFERROR(INDEX(Items!$C$2:$C$500,MATCH(I7,Items!$H$2:$H$500,0)),"UNKNOWN") -> Barrier | K7: =IF(J7="UNKNOWN","",INDEX(Items!$F$2:$F$500,MATCH(I7,Items!$H$2:$H$500,0))) -> 1450 | L7: =IF(ISNUMBER(H7),G7*H7,"") -> 27961.71 | M7: =IF(ISNUMBER(H7),G7,0) -> 21 | N7: =IF(AND(ISNUMBER(H7),ISNUMBER(K7)),1-H7/K7,"") -> 0.081717241 | O7: =IF(J7="UNKNOWN","",INDEX(Cost_Rollup!$F$5:$F$16,MATCH(I7,Cost_Rollup!$A$5:$A$16,0))) -> 978.66328 | P7: =IF(AND(ISNUMBER(L7),ISNUMBER(O7)),G7*O7,"") -> 20551.929 | Q7: =IF(H7="","Missing price; ","")&IF(J7="UNKNOWN","Unknown item; ","")&IF(AND(ISNUMBER(N7),N7>Discount_Threshold),"Discount above limit; ","") | R7: =IF(Q7="","OK","CHECK") -> OK
A8: INV-25128 | B8: 45668 | C8: CUST-002 | D8: AB | E8: CA | F8: PC-RCP-1200 | G8: 14 | H8: 1958.27 | I8: =UPPER(TRIM(F8)) -> PC-RCP-1200 | J8: =IFERROR(INDEX(Items!$C$2:$C$500,MATCH(I8,Items!$H$2:$H$500,0)),"UNKNOWN") -> Pipe | K8: =IF(J8="UNKNOWN","",INDEX(Items!$F$2:$F$500,MATCH(I8,Items!$H$2:$H$500,0))) -> 1890 | L8: =IF(ISNUMBER(H8),G8*H8,"") -> 27415.78 | M8: =IF(ISNUMBER(H8),G8,0) -> 14 | N8: =IF(AND(ISNUMBER(H8),ISNUMBER(K8)),1-H8/K8,"") -> -0.036121693 | O8: =IF(J8="UNKNOWN","",INDEX(Cost_Rollup!$F$5:$F$16,MATCH(I8,Cost_Rollup!$A$5:$A$16,0))) -> 1206.4054 | P8: =IF(AND(ISNUMBER(L8),ISNUMBER(O8)),G8*O8,"") -> 16889.676 | Q8: =IF(H8="","Missing price; ","")&IF(J8="UNKNOWN","Unknown item; ","")&IF(AND(ISNUMBER(N8),N8>Discount_Threshold),"Discount above limit; ","") | R8: =IF(Q8="","OK","CHECK") -> OK
A9: INV-25029 | B9: 45670 | C9: CUST-002 | D9: AB | E9: CA | F9: PC-RCP-0600 | G9: 18 | H9: 628.03 | I9: =UPPER(TRIM(F9)) -> PC-RCP-0600 | J9: =IFERROR(INDEX(Items!$C$2:$C$500,MATCH(I9,Items!$H$2:$H$500,0)),"UNKNOWN") -> Pipe | K9: =IF(J9="UNKNOWN","",INDEX(Items!$F$2:$F$500,MATCH(I9,Items!$H$2:$H$500,0))) -> 640 | L9: =IF(ISNUMBER(H9),G9*H9,"") -> 11304.54 | M9: =IF(ISNUMBER(H9),G9,0) -> 18 | N9: =IF(AND(ISNUMBER(H9),ISNUMBER(K9)),1-H9/K9,"") -> 0.018703125 | O9: =IF(J9="UNKNOWN","",INDEX(Cost_Rollup!$F$5:$F$16,MATCH(I9,Cost_Rollup!$A$5:$A$16,0))) -> 429.94832 | P9: =IF(AND(ISNUMBER(L9),ISNUMBER(O9)),G9*O9,"") -> 7739.0698 | Q9: =IF(H9="","Missing price; ","")&IF(J9="UNKNOWN","Unknown item; ","")&IF(AND(ISNUMBER(N9),N9>Discount_Threshold),"Discount above limit; ","") | R9: =IF(Q9="","OK","CHECK") -> OK
A10: INV-25201 | B10: 45670 | C10: CUST-007 | D10: MT | E10: US | F10: PC-MH-1200R | G10: 2 | H10: 500.11 | I10: =UPPER(TRIM(F10)) -> PC-MH-1200R | J10: =IFERROR(INDEX(Items!$C$2:$C$500,MATCH(I10,Items!$H$2:$H$500,0)),"UNKNOWN") -> Manhole | K10: =IF(J10="UNKNOWN","",INDEX(Items!$F$2:$F$500,MATCH(I10,Items!$H$2:$H$500,0))) -> 520 | L10: =IF(ISNUMBER(H10),G10*H10,"") -> 1000.22 | M10: =IF(ISNUMBER(H10),G10,0) -> 2 | N10: =IF(AND(ISNUMBER(H10),ISNUMBER(K10)),1-H10/K10,"") -> 0.03825 | O10: =IF(J10="UNKNOWN","",INDEX(Cost_Rollup!$F$5:$F$16,MATCH(I10,Cost_Rollup!$A$5:$A$16,0))) -> 381.98428 | P10: =IF(AND(ISNUMBER(L10),ISNUMBER(O10)),G10*O10,"") -> 763.96856 | Q10: =IF(H10="","Missing price; ","")&IF(J10="UNKNOWN","Unknown item; ","")&IF(AND(ISNUMBER(N10),N10>Discount_Threshold),"Discount above limit; ","") | R10: =IF(Q10="","OK","CHECK") -> OK
A11: INV-25091 | B11: 45672 | C11: CUST-009 | D11: SK | E11: CA | F11: PC-BOX-1812 | G11: 6 | H11: 4116.71 | I11: =UPPER(TRIM(F11)) -> PC-BOX-1812 | J11: =IFERROR(INDEX(Items!$C$2:$C$500,MATCH(I11,Items!$H$2:$H$500,0)),"UNKNOWN") -> Box Culvert | K11: =IF(J11="UNKNOWN","",INDEX(Items!$F$2:$F$500,MATCH(I11,Items!$H$2:$H$500,0))) -> 4200 | L11: =IF(ISNUMBER(H11),G11*H11,"") -> 24700.26 | M11: =IF(ISNUMBER(H11),G11,0) -> 6 | N11: =IF(AND(ISNUMBER(H11),ISNUMBER(K11)),1-H11/K11,"") -> 0.019830952 | O11: =IF(J11="UNKNOWN","",INDEX(Cost_Rollup!$F$5:$F$16,MATCH(I11,Cost_Rollup!$A$5:$A$16,0))) -> 2795.3624 | P11: =IF(AND(ISNUMBER(L11),ISNUMBER(O11)),G11*O11,"") -> 16772.174 | Q11: =IF(H11="","Missing price; ","")&IF(J11="UNKNOWN","Unknown item; ","")&IF(AND(ISNUMBER(N11),N11>Discount_Threshold),"Discount above limit; ","") | R11: =IF(Q11="","OK","CHECK") -> OK
A12: INV-25217 | B12: 45673 | C12: CUST-008 | D12: ND | E12: US | F12: PC-BAR-SS60 | G12: 23 | H12: 2427.02 | I12: =UPPER(TRIM(F12)) -> PC-BAR-SS60 | J12: =IFERROR(INDEX(Items!$C$2:$C$500,MATCH(I12,Items!$H$2:$H$500,0)),"UNKNOWN") -> Barrier | K12: =IF(J12="UNKNOWN","",INDEX(Items!$F$2:$F$500,MATCH(I12,Items!$H$2:$H$500,0))) -> 2350 | L12: =IF(ISNUMBER(H12),G12*H12,"") -> 55821.46 | M12: =IF(ISNUMBER(H12),G12,0) -> 23 | N12: =IF(AND(ISNUMBER(H12),ISNUMBER(K12)),1-H12/K12,"") -> -0.032774468 | O12: =IF(J12="UNKNOWN","",INDEX(Cost_Rollup!$F$5:$F$16,MATCH(I12,Cost_Rollup!$A$5:$A$16,0))) -> 1583.5454 | P12: =IF(AND(ISNUMBER(L12),ISNUMBER(O12)),G12*O12,"") -> 36421.544 | Q12: =IF(H12="","Missing price; ","")&IF(J12="UNKNOWN","Unknown item; ","")&IF(AND(ISNUMBER(N12),N12>Discount_Threshold),"Discount above limit; ","") | R12: =IF(Q12="","OK","CHECK") -> OK
A13: INV-25135 | B13: 45674 | C13: CUST-008 | D13: ND | E13: US | F13: PC-MH-1200B | G13: 5 | H13: 1261.22 | I13: =UPPER(TRIM(F13)) -> PC-MH-1200B | J13: =IFERROR(INDEX(Items!$C$2:$C$500,MATCH(I13,Items!$H$2:$H$500,0)),"UNKNOWN") -> Manhole | K13: =IF(J13="UNKNOWN","",INDEX(Items!$F$2:$F$500,MATCH(I13,Items!$H$2:$H$500,0))) -> 1240 | L13: =IF(ISNUMBER(H13),G13*H13,"") -> 6306.1 | M13: =IF(ISNUMBER(H13),G13,0) -> 5 | N13: =IF(AND(ISNUMBER(H13),ISNUMBER(K13)),1-H13/K13,"") -> -0.017112903 | O13: =IF(J13="UNKNOWN","",INDEX(Cost_Rollup!$F$5:$F$16,MATCH(I13,Cost_Rollup!$A$5:$A$16,0))) -> 753.4208 | P13: =IF(AND(ISNUMBER(L13),ISNUMBER(O13)),G13*O13,"") -> 3767.104 | Q13: =IF(H13="","Missing price; ","")&IF(J13="UNKNOWN","Unknown item; ","")&IF(AND(ISNUMBER(N13),N13>Discount_Threshold),"Discount above limit; ","") | R13: =IF(Q13="","OK","CHECK") -> OK
... A161: INV-25228 | B161: 45894 | C161: CUST-004 | D161: BC | E161: CA | F161: PC-RCP-1200 | G161: 20 | H161: 1780.92 | I161: =UPPER(TRIM(F161)) -> PC-RCP-1200 | J161: =IFERROR(INDEX(Items!$C$2:$C$500,MATCH(I161,Items!$H$2:$H$500,0)),"UNKNOWN") -> Pipe | K161: =IF(J161="UNKNOWN","",INDEX(Items!$F$2:$F$500,MATCH(I161,Items!$H$2:$H$500,0))) -> 1890 | L161: =IF(ISNUMBER(H161),G161*H161,"") -> 35618.4 | M161: =IF(ISNUMBER(H161),G161,0) -> 20 | N161: =IF(AND(ISNUMBER(H161),ISNUMBER(K161)),1-H161/K161,"") -> 0.057714286 | O161: =IF(J161="UNKNOWN","",INDEX(Cost_Rollup!$F$5:$F$16,MATCH(I161,Cost_Rollup!$A$5:$A$16,0))) -> 1206.4054 | P161: =IF(AND(ISNUMBER(L161),ISNUMBER(O161)),G161*O161,"") -> 24128.108 | Q161: =IF(H161="","Missing price; ","")&IF(J161="UNKNOWN","Unknown item; ","")&IF(AND(ISNUMBER(N161),N161>Discount_Threshold),"Discount above limit; ","") | R161: =IF(Q161="","OK","CHECK") -> OK
A162: INV-25018 | B162: 45896 | C162: CUST-008 | D162: ND | E162: US | F162: PC-HC-250 | G162: 319 | I162: =UPPER(TRIM(F162)) -> PC-HC-250 | J162: =IFERROR(INDEX(Items!$C$2:$C$500,MATCH(I162,Items!$H$2:$H$500,0)),"UNKNOWN") -> Slab | K162: =IF(J162="UNKNOWN","",INDEX(Items!$F$2:$F$500,MATCH(I162,Items!$H$2:$H$500,0))) -> 136 | L162: =IF(ISNUMBER(H162),G162*H162,"") | M162: =IF(ISNUMBER(H162),G162,0) -> 0 | N162: =IF(AND(ISNUMBER(H162),ISNUMBER(K162)),1-H162/K162,"") | O162: =IF(J162="UNKNOWN","",INDEX(Cost_Rollup!$F$5:$F$16,MATCH(I162,Cost_Rollup!$A$5:$A$16,0))) -> 92.94024 | P162: =IF(AND(ISNUMBER(L162),ISNUMBER(O162)),G162*O162,"") | Q162: =IF(H162="","Missing price; ","")&IF(J162="UNKNOWN","Unknown item; ","")&IF(AND(ISNUMBER(N162),N162>Discount_Threshold),"Discount above limit; ","") -> Missing price; | R162: =IF(Q162="","OK","CHECK") -> CHECK
A163: INV-25022 | B163: 45897 | C163: CUST-009 | D163: SK | E163: CA | F163: PC-CB-0600 | G163: 7 | H163: 710.02 | I163: =UPPER(TRIM(F163)) -> PC-CB-0600 | J163: =IFERROR(INDEX(Items!$C$2:$C$500,MATCH(I163,Items!$H$2:$H$500,0)),"UNKNOWN") -> Catch Basin | K163: =IF(J163="UNKNOWN","",INDEX(Items!$F$2:$F$500,MATCH(I163,Items!$H$2:$H$500,0))) -> 690 | L163: =IF(ISNUMBER(H163),G163*H163,"") -> 4970.14 | M163: =IF(ISNUMBER(H163),G163,0) -> 7 | N163: =IF(AND(ISNUMBER(H163),ISNUMBER(K163)),1-H163/K163,"") -> -0.029014493 | O163: =IF(J163="UNKNOWN","",INDEX(Cost_Rollup!$F$5:$F$16,MATCH(I163,Cost_Rollup!$A$5:$A$16,0))) -> 471.0488 | P163: =IF(AND(ISNUMBER(L163),ISNUMBER(O163)),G163*O163,"") -> 3297.3416 | Q163: =IF(H163="","Missing price; ","")&IF(J163="UNKNOWN","Unknown item; ","")&IF(AND(ISNUMBER(N163),N163>Discount_Threshold),"Discount above limit; ","") | R163: =IF(Q163="","OK","CHECK") -> OK
A164: INV-25086 | B164: 45897 | C164: CUST-009 | D164: SK | E164: CA | F164: PC-CB-0600 | G164: 12 | H164: 677.08 | I164: =UPPER(TRIM(F164)) -> PC-CB-0600 | J164: =IFERROR(INDEX(Items!$C$2:$C$500,MATCH(I164,Items!$H$2:$H$500,0)),"UNKNOWN") -> Catch Basin | K164: =IF(J164="UNKNOWN","",INDEX(Items!$F$2:$F$500,MATCH(I164,Items!$H$2:$H$500,0))) -> 690 | L164: =IF(ISNUMBER(H164),G164*H164,"") -> 8124.96 | M164: =IF(ISNUMBER(H164),G164,0) -> 12 | N164: =IF(AND(ISNUMBER(H164),ISNUMBER(K164)),1-H164/K164,"") -> 0.018724638 | O164: =IF(J164="UNKNOWN","",INDEX(Cost_Rollup!$F$5:$F$16,MATCH(I164,Cost_Rollup!$A$5:$A$16,0))) -> 471.0488 | P164: =IF(AND(ISNUMBER(L164),ISNUMBER(O164)),G164*O164,"") -> 5652.5856 | Q164: =IF(H164="","Missing price; ","")&IF(J164="UNKNOWN","Unknown item; ","")&IF(AND(ISNUMBER(N164),N164>Discount_Threshold),"Discount above limit; ","") | R164: =IF(Q164="","OK","CHECK") -> OK
A165: INV-25049 | B165: 45900 | C165: CUST-008 | D165: ND | E165: US | F165: PC-MH-1200R | G165: 5 | H165: 502.05 | I165: =UPPER(TRIM(F165)) -> PC-MH-1200R | J165: =IFERROR(INDEX(Items!$C$2:$C$500,MATCH(I165,Items!$H$2:$H$500,0)),"UNKNOWN") -> Manhole | K165: =IF(J165="UNKNOWN","",INDEX(Items!$F$2:$F$500,MATCH(I165,Items!$H$2:$H$500,0))) -> 520 | L165: =IF(ISNUMBER(H165),G165*H165,"") -> 2510.25 | M165: =IF(ISNUMBER(H165),G165,0) -> 5 | N165: =IF(AND(ISNUMBER(H165),ISNUMBER(K165)),1-H165/K165,"") -> 0.034519231 | O165: =IF(J165="UNKNOWN","",INDEX(Cost_Rollup!$F$5:$F$16,MATCH(I165,Cost_Rollup!$A$5:$A$16,0))) -> 381.98428 | P165: =IF(AND(ISNUMBER(L165),ISNUMBER(O165)),G165*O165,"") -> 1909.9214 | Q165: =IF(H165="","Missing price; ","")&IF(J165="UNKNOWN","Unknown item; ","")&IF(AND(ISNUMBER(N165),N165>Discount_Threshold),"Discount above limit; ","") | R165: =IF(Q165="","OK","CHECK") -> OK
A166: INV-25111 | B166: 45900 | C166: CUST-004 | D166: BC | E166: CA | F166: PC-HC-250 | G166: 218 | H166: 136.85 | I166: =UPPER(TRIM(F166)) -> PC-HC-250 | J166: =IFERROR(INDEX(Items!$C$2:$C$500,MATCH(I166,Items!$H$2:$H$500,0)),"UNKNOWN") -> Slab | K166: =IF(J166="UNKNOWN","",INDEX(Items!$F$2:$F$500,MATCH(I166,Items!$H$2:$H$500,0))) -> 136 | L166: =IF(ISNUMBER(H166),G166*H166,"") -> 29833.3 | M166: =IF(ISNUMBER(H166),G166,0) -> 218 | N166: =IF(AND(ISNUMBER(H166),ISNUMBER(K166)),1-H166/K166,"") -> -0.00625 | O166: =IF(J166="UNKNOWN","",INDEX(Cost_Rollup!$F$5:$F$16,MATCH(I166,Cost_Rollup!$A$5:$A$16,0))) -> 92.94024 | P166: =IF(AND(ISNUMBER(L166),ISNUMBER(O166)),G166*O166,"") -> 20260.972 | Q166: =IF(H166="","Missing price; ","")&IF(J166="UNKNOWN","Unknown item; ","")&IF(AND(ISNUMBER(N166),N166>Discount_Threshold),"Discount above limit; ","") | R166: =IF(Q166="","OK","CHECK") -> OK
A167: INV-25129 | B167: 45900 | C167: CUST-004 | D167: BC | E167: CA | F167: PC-BAR-SS60 | G167: 15 | H167: 2347.11 | I167: =UPPER(TRIM(F167)) -> PC-BAR-SS60 | J167: =IFERROR(INDEX(Items!$C$2:$C$500,MATCH(I167,Items!$H$2:$H$500,0)),"UNKNOWN") -> Barrier | K167: =IF(J167="UNKNOWN","",INDEX(Items!$F$2:$F$500,MATCH(I167,Items!$H$2:$H$500,0))) -> 2350 | L167: =IF(ISNUMBER(H167),G167*H167,"") -> 35206.65 | M167: =IF(ISNUMBER(H167),G167,0) -> 15 | N167: =IF(AND(ISNUMBER(H167),ISNUMBER(K167)),1-H167/K167,"") -> 0.0012297872 | O167: =IF(J167="UNKNOWN","",INDEX(Cost_Rollup!$F$5:$F$16,MATCH(I167,Cost_Rollup!$A$5:$A$16,0))) -> 1583.5454 | P167: =IF(AND(ISNUMBER(L167),ISNUMBER(O167)),G167*O167,"") -> 23753.181 | Q167: =IF(H167="","Missing price; ","")&IF(J167="UNKNOWN","Unknown item; ","")&IF(AND(ISNUMBER(N167),N167>Discount_Threshold),"Discount above limit; ","") | R167: =IF(Q167="","OK","CHECK") -> OK
A168: INV-25136 | B168: 45901 | C168: CUST-004 | D168: BC | E168: CA | F168: PC-MH-1200B | G168: 5 | H168: 1204.93 | I168: =UPPER(TRIM(F168)) -> PC-MH-1200B | J168: =IFERROR(INDEX(Items!$C$2:$C$500,MATCH(I168,Items!$H$2:$H$500,0)),"UNKNOWN") -> Manhole | K168: =IF(J168="UNKNOWN","",INDEX(Items!$F$2:$F$500,MATCH(I168,Items!$H$2:$H$500,0))) -> 1240 | L168: =IF(ISNUMBER(H168),G168*H168,"") -> 6024.65 | M168: =IF(ISNUMBER(H168),G168,0) -> 5 | N168: =IF(AND(ISNUMBER(H168),ISNUMBER(K168)),1-H168/K168,"") -> 0.028282258 | O168: =IF(J168="UNKNOWN","",INDEX(Cost_Rollup!$F$5:$F$16,MATCH(I168,Cost_Rollup!$A$5:$A$16,0))) -> 753.4208 | P168: =IF(AND(ISNUMBER(L168),ISNUMBER(O168)),G168*O168,"") -> 3767.104 | Q168: =IF(H168="","Missing price; ","")&IF(J168="UNKNOWN","Unknown item; ","")&IF(AND(ISNUMBER(N168),N168>Discount_Threshold),"Discount above limit; ","") | R168: =IF(Q168="","OK","CHECK") -> OK
A169: INV-25180 | B169: 45902 | C169: CUST-004 | D169: BC | E169: CA | F169: PC-MH-1200R | G169: 4 | H169: 505.43 | I169: =UPPER(TRIM(F169)) -> PC-MH-1200R | J169: =IFERROR(INDEX(Items!$C$2:$C$500,MATCH(I169,Items!$H$2:$H$500,0)),"UNKNOWN") -> Manhole | K169: =IF(J169="UNKNOWN","",INDEX(Items!$F$2:$F$500,MATCH(I169,Items!$H$2:$H$500,0))) -> 520 | L169: =IF(ISNUMBER(H169),G169*H169,"") -> 2021.72 | M169: =IF(ISNUMBER(H169),G169,0) -> 4 | N169: =IF(AND(ISNUMBER(H169),ISNUMBER(K169)),1-H169/K169,"") -> 0.028019231 | O169: =IF(J169="UNKNOWN","",INDEX(Cost_Rollup!$F$5:$F$16,MATCH(I169,Cost_Rollup!$A$5:$A$16,0))) -> 381.98428 | P169: =IF(AND(ISNUMBER(L169),ISNUMBER(O169)),G169*O169,"") -> 1527.9371 | Q169: =IF(H169="","Missing price; ","")&IF(J169="UNKNOWN","Unknown item; ","")&IF(AND(ISNUMBER(N169),N169>Discount_Threshold),"Discount above limit; ","") | R169: =IF(Q169="","OK","CHECK") -> OK
A170: INV-25194 | B170: 45902 | C170: CUST-009 | D170: SK | E170: CA | F170: PC-HC-200 | G170: 57 | H170: 122.01 | I170: =UPPER(TRIM(F170)) -> PC-HC-200 | J170: =IFERROR(INDEX(Items!$C$2:$C$500,MATCH(I170,Items!$H$2:$H$500,0)),"UNKNOWN") -> Slab | K170: =IF(J170="UNKNOWN","",INDEX(Items!$F$2:$F$500,MATCH(I170,Items!$H$2:$H$500,0))) -> 118 | L170: =IF(ISNUMBER(H170),G170*H170,"") -> 6954.57 | M170: =IF(ISNUMBER(H170),G170,0) -> 57 | N170: =IF(AND(ISNUMBER(H170),ISNUMBER(K170)),1-H170/K170,"") -> -0.033983051 | O170: =IF(J170="UNKNOWN","",INDEX(Cost_Rollup!$F$5:$F$16,MATCH(I170,Cost_Rollup!$A$5:$A$16,0))) -> 78.89382 | P170: =IF(AND(ISNUMBER(L170),ISNUMBER(O170)),G170*O170,"") -> 4496.9477 | Q170: =IF(H170="","Missing price; ","")&IF(J170="UNKNOWN","Unknown item; ","")&IF(AND(ISNUMBER(N170),N170>Discount_Threshold),"Discount above limit; ","") | R170: =IF(Q170="","OK","CHECK") -> OK
A171: INV-25214 | B171: 45904 | C171: CUST-003 | D171: SK | E171: CA | F171: PC-BAR-SS60 | G171: 37 | H171: 2421.87 | I171: =UPPER(TRIM(F171)) -> PC-BAR-SS60 | J171: =IFERROR(INDEX(Items!$C$2:$C$500,MATCH(I171,Items!$H$2:$H$500,0)),"UNKNOWN") -> Barrier | K171: =IF(J171="UNKNOWN","",INDEX(Items!$F$2:$F$500,MATCH(I171,Items!$H$2:$H$500,0))) -> 2350 | L171: =IF(ISNUMBER(H171),G171*H171,"") -> 89609.19 | M171: =IF(ISNUMBER(H171),G171,0) -> 37 | N171: =IF(AND(ISNUMBER(H171),ISNUMBER(K171)),1-H171/K171,"") -> -0.030582979 | O171: =IF(J171="UNKNOWN","",INDEX(Cost_Rollup!$F$5:$F$16,MATCH(I171,Cost_Rollup!$A$5:$A$16,0))) -> 1583.5454 | P171: =IF(AND(ISNUMBER(L171),ISNUMBER(O171)),G171*O171,"") -> 58591.18 | Q171: =IF(H171="","Missing price; ","")&IF(J171="UNKNOWN","Unknown item; ","")&IF(AND(ISNUMBER(N171),N171>Discount_Threshold),"Discount above limit; ","") | R171: =IF(Q171="","OK","CHECK") -> OK
A172: INV-25206 | B172: 45905 | C172: CUST-003 | D172: SK | E172: CA | F172: PC-HC-200 | G172: 205 | H172: 109.1 | I172: =UPPER(TRIM(F172)) -> PC-HC-200 | J172: =IFERROR(INDEX(Items!$C$2:$C$500,MATCH(I172,Items!$H$2:$H$500,0)),"UNKNOWN") -> Slab | K172: =IF(J172="UNKNOWN","",INDEX(Items!$F$2:$F$500,MATCH(I172,Items!$H$2:$H$500,0))) -> 118 | L172: =IF(ISNUMBER(H172),G172*H172,"") -> 22365.5 | M172: =IF(ISNUMBER(H172),G172,0) -> 205 | N172: =IF(AND(ISNUMBER(H172),ISNUMBER(K172)),1-H172/K172,"") -> 0.075423729 | O172: =IF(J172="UNKNOWN","",INDEX(Cost_Rollup!$F$5:$F$16,MATCH(I172,Cost_Rollup!$A$5:$A$16,0))) -> 78.89382 | P172: =IF(AND(ISNUMBER(L172),ISNUMBER(O172)),G172*O172,"") -> 16173.233 | Q172: =IF(H172="","Missing price; ","")&IF(J172="UNKNOWN","Unknown item; ","")&IF(AND(ISNUMBER(N172),N172>Discount_Threshold),"Discount above limit; ","") | R172: =IF(Q172="","OK","CHECK") -> OK
A173: INV-25251 | B173: 45906 | C173: CUST-006 | D173: AB | E173: CA | F173: PC-HC-250 | G173: 90 | H173: 141.4 | I173: =UPPER(TRIM(F173)) -> PC-HC-250 | J173: =IFERROR(INDEX(Items!$C$2:$C$500,MATCH(I173,Items!$H$2:$H$500,0)),"UNKNOWN") -> Slab | K173: =IF(J173="UNKNOWN","",INDEX(Items!$F$2:$F$500,MATCH(I173,Items!$H$2:$H$500,0))) -> 136 | L173: =IF(ISNUMBER(H173),G173*H173,"") -> 12726 | M173: =IF(ISNUMBER(H173),G173,0) -> 90 | N173: =IF(AND(ISNUMBER(H173),ISNUMBER(K173)),1-H173/K173,"") -> -0.039705882 | O173: =IF(J173="UNKNOWN","",INDEX(Cost_Rollup!$F$5:$F$16,MATCH(I173,Cost_Rollup!$A$5:$A$16,0))) -> 92.94024 | P173: =IF(AND(ISNUMBER(L173),ISNUMBER(O173)),G173*O173,"") -> 8364.6216 | Q173: =IF(H173="","Missing price; ","")&IF(J173="UNKNOWN","Unknown item; ","")&IF(AND(ISNUMBER(N173),N173>Discount_Threshold),"Discount above limit; ","") | R173: =IF(Q173="","OK","CHECK") -> OK
A174: INV-25167 | B174: 45907 | C174: CUST-009 | D174: SK | E174: CA | F174: PC-CB-0600 | G174: 6 | H174: 702.19 | I174: =UPPER(TRIM(F174)) -> PC-CB-0600 | J174: =IFERROR(INDEX(Items!$C$2:$C$500,MATCH(I174,Items!$H$2:$H$500,0)),"UNKNOWN") -> Catch Basin | K174: =IF(J174="UNKNOWN","",INDEX(Items!$F$2:$F$500,MATCH(I174,Items!$H$2:$H$500,0))) -> 690 | L174: =IF(ISNUMBER(H174),G174*H174,"") -> 4213.14 | M174: =IF(ISNUMBER(H174),G174,0) -> 6 | N174: =IF(AND(ISNUMBER(H174),ISNUMBER(K174)),1-H174/K174,"") -> -0.017666667 | O174: =IF(J174="UNKNOWN","",INDEX(Cost_Rollup!$F$5:$F$16,MATCH(I174,Cost_Rollup!$A$5:$A$16,0))) -> 471.0488 | P174: =IF(AND(ISNUMBER(L174),ISNUMBER(O174)),G174*O174,"") -> 2826.2928 | Q174: =IF(H174="","Missing price; ","")&IF(J174="UNKNOWN","Unknown item; ","")&IF(AND(ISNUMBER(N174),N174>Discount_Threshold),"Discount above limit; ","") | R174: =IF(Q174="","OK","CHECK") -> OK
... A243: INV-25231 | B243: 45988 | C243: CUST-008 | D243: ND | E243: US | F243: PC-HC-200 | G243: 70 | H243: 116.31 | I243: =UPPER(TRIM(F243)) -> PC-HC-200 | J243: =IFERROR(INDEX(Items!$C$2:$C$500,MATCH(I243,Items!$H$2:$H$500,0)),"UNKNOWN") -> Slab | K243: =IF(J243="UNKNOWN","",INDEX(Items!$F$2:$F$500,MATCH(I243,Items!$H$2:$H$500,0))) -> 118 | L243: =IF(ISNUMBER(H243),G243*H243,"") -> 8141.7 | M243: =IF(ISNUMBER(H243),G243,0) -> 70 | N243: =IF(AND(ISNUMBER(H243),ISNUMBER(K243)),1-H243/K243,"") -> 0.014322034 | O243: =IF(J243="UNKNOWN","",INDEX(Cost_Rollup!$F$5:$F$16,MATCH(I243,Cost_Rollup!$A$5:$A$16,0))) -> 78.89382 | P243: =IF(AND(ISNUMBER(L243),ISNUMBER(O243)),G243*O243,"") -> 5522.5674 | Q243: =IF(H243="","Missing price; ","")&IF(J243="UNKNOWN","Unknown item; ","")&IF(AND(ISNUMBER(N243),N243>Discount_Threshold),"Discount above limit; ","") | R243: =IF(Q243="","OK","CHECK") -> OK
A244: INV-25089 | B244: 45990 | C244: CUST-003 | D244: SK | E244: CA | F244: PC-RCP-0900 | G244: 13 | I244: =UPPER(TRIM(F244)) -> PC-RCP-0900 | J244: =IFERROR(INDEX(Items!$C$2:$C$500,MATCH(I244,Items!$H$2:$H$500,0)),"UNKNOWN") -> Pipe | K244: =IF(J244="UNKNOWN","",INDEX(Items!$F$2:$F$500,MATCH(I244,Items!$H$2:$H$500,0))) -> 1150 | L244: =IF(ISNUMBER(H244),G244*H244,"") | M244: =IF(ISNUMBER(H244),G244,0) -> 0 | N244: =IF(AND(ISNUMBER(H244),ISNUMBER(K244)),1-H244/K244,"") | O244: =IF(J244="UNKNOWN","",INDEX(Cost_Rollup!$F$5:$F$16,MATCH(I244,Cost_Rollup!$A$5:$A$16,0))) -> 750.43373 | P244: =IF(AND(ISNUMBER(L244),ISNUMBER(O244)),G244*O244,"") | Q244: =IF(H244="","Missing price; ","")&IF(J244="UNKNOWN","Unknown item; ","")&IF(AND(ISNUMBER(N244),N244>Discount_Threshold),"Discount above limit; ","") -> Missing price; | R244: =IF(Q244="","OK","CHECK") -> CHECK
A245: INV-25010 | B245: 45993 | C245: CUST-010 | D245: BC | E245: CA | F245: PC-MH-1050B | G245: 1 | H245: 998.32 | I245: =UPPER(TRIM(F245)) -> PC-MH-1050B | J245: =IFERROR(INDEX(Items!$C$2:$C$500,MATCH(I245,Items!$H$2:$H$500,0)),"UNKNOWN") -> Manhole | K245: =IF(J245="UNKNOWN","",INDEX(Items!$F$2:$F$500,MATCH(I245,Items!$H$2:$H$500,0))) -> 980 | L245: =IF(ISNUMBER(H245),G245*H245,"") -> 998.32 | M245: =IF(ISNUMBER(H245),G245,0) -> 1 | N245: =IF(AND(ISNUMBER(H245),ISNUMBER(K245)),1-H245/K245,"") -> -0.018693878 | O245: =IF(J245="UNKNOWN","",INDEX(Cost_Rollup!$F$5:$F$16,MATCH(I245,Cost_Rollup!$A$5:$A$16,0))) -> 635.433 | P245: =IF(AND(ISNUMBER(L245),ISNUMBER(O245)),G245*O245,"") -> 635.433 | Q245: =IF(H245="","Missing price; ","")&IF(J245="UNKNOWN","Unknown item; ","")&IF(AND(ISNUMBER(N245),N245>Discount_Threshold),"Discount above limit; ","") | R245: =IF(Q245="","OK","CHECK") -> OK
A246: INV-25038 | B246: 45993 | C246: CUST-006 | D246: AB | E246: CA | F246: PC-RCP-0600 | G246: 4 | H246: 621.73 | I246: =UPPER(TRIM(F246)) -> PC-RCP-0600 | J246: =IFERROR(INDEX(Items!$C$2:$C$500,MATCH(I246,Items!$H$2:$H$500,0)),"UNKNOWN") -> Pipe | K246: =IF(J246="UNKNOWN","",INDEX(Items!$F$2:$F$500,MATCH(I246,Items!$H$2:$H$500,0))) -> 640 | L246: =IF(ISNUMBER(H246),G246*H246,"") -> 2486.92 | M246: =IF(ISNUMBER(H246),G246,0) -> 4 | N246: =IF(AND(ISNUMBER(H246),ISNUMBER(K246)),1-H246/K246,"") -> 0.028546875 | O246: =IF(J246="UNKNOWN","",INDEX(Cost_Rollup!$F$5:$F$16,MATCH(I246,Cost_Rollup!$A$5:$A$16,0))) -> 429.94832 | P246: =IF(AND(ISNUMBER(L246),ISNUMBER(O246)),G246*O246,"") -> 1719.7933 | Q246: =IF(H246="","Missing price; ","")&IF(J246="UNKNOWN","Unknown item; ","")&IF(AND(ISNUMBER(N246),N246>Discount_Threshold),"Discount above limit; ","") | R246: =IF(Q246="","OK","CHECK") -> OK
A247: INV-25204 | B247: 45993 | C247: CUST-003 | D247: SK | E247: CA | F247: PC-CB-0600 | G247: 3 | H247: 622.83 | I247: =UPPER(TRIM(F247)) -> PC-CB-0600 | J247: =IFERROR(INDEX(Items!$C$2:$C$500,MATCH(I247,Items!$H$2:$H$500,0)),"UNKNOWN") -> Catch Basin | K247: =IF(J247="UNKNOWN","",INDEX(Items!$F$2:$F$500,MATCH(I247,Items!$H$2:$H$500,0))) -> 690 | L247: =IF(ISNUMBER(H247),G247*H247,"") -> 1868.49 | M247: =IF(ISNUMBER(H247),G247,0) -> 3 | N247: =IF(AND(ISNUMBER(H247),ISNUMBER(K247)),1-H247/K247,"") -> 0.097347826 | O247: =IF(J247="UNKNOWN","",INDEX(Cost_Rollup!$F$5:$F$16,MATCH(I247,Cost_Rollup!$A$5:$A$16,0))) -> 471.0488 | P247: =IF(AND(ISNUMBER(L247),ISNUMBER(O247)),G247*O247,"") -> 1413.1464 | Q247: =IF(H247="","Missing price; ","")&IF(J247="UNKNOWN","Unknown item; ","")&IF(AND(ISNUMBER(N247),N247>Discount_Threshold),"Discount above limit; ","") | R247: =IF(Q247="","OK","CHECK") -> OK
A248: INV-25043 | B248: 45994 | C248: CUST-003 | D248: SK | E248: CA | F248: PC-RCP-0600 | G248: 24 | H248: 624.81 | I248: =UPPER(TRIM(F248)) -> PC-RCP-0600 | J248: =IFERROR(INDEX(Items!$C$2:$C$500,MATCH(I248,Items!$H$2:$H$500,0)),"UNKNOWN") -> Pipe | K248: =IF(J248="UNKNOWN","",INDEX(Items!$F$2:$F$500,MATCH(I248,Items!$H$2:$H$500,0))) -> 640 | L248: =IF(ISNUMBER(H248),G248*H248,"") -> 14995.44 | M248: =IF(ISNUMBER(H248),G248,0) -> 24 | N248: =IF(AND(ISNUMBER(H248),ISNUMBER(K248)),1-H248/K248,"") -> 0.023734375 | O248: =IF(J248="UNKNOWN","",INDEX(Cost_Rollup!$F$5:$F$16,MATCH(I248,Cost_Rollup!$A$5:$A$16,0))) -> 429.94832 | P248: =IF(AND(ISNUMBER(L248),ISNUMBER(O248)),G248*O248,"") -> 10318.76 | Q248: =IF(H248="","Missing price; ","")&IF(J248="UNKNOWN","Unknown item; ","")&IF(AND(ISNUMBER(N248),N248>Discount_Threshold),"Discount above limit; ","") | R248: =IF(Q248="","OK","CHECK") -> OK
A249: INV-25121 | B249: 45994 | C249: CUST-006 | D249: AB | E249: CA | F249: PC-RCP-0600 | G249: 16 | H249: 640.91 | I249: =UPPER(TRIM(F249)) -> PC-RCP-0600 | J249: =IFERROR(INDEX(Items!$C$2:$C$500,MATCH(I249,Items!$H$2:$H$500,0)),"UNKNOWN") -> Pipe | K249: =IF(J249="UNKNOWN","",INDEX(Items!$F$2:$F$500,MATCH(I249,Items!$H$2:$H$500,0))) -> 640 | L249: =IF(ISNUMBER(H249),G249*H249,"") -> 10254.56 | M249: =IF(ISNUMBER(H249),G249,0) -> 16 | N249: =IF(AND(ISNUMBER(H249),ISNUMBER(K249)),1-H249/K249,"") -> -0.001421875 | O249: =IF(J249="UNKNOWN","",INDEX(Cost_Rollup!$F$5:$F$16,MATCH(I249,Cost_Rollup!$A$5:$A$16,0))) -> 429.94832 | P249: =IF(AND(ISNUMBER(L249),ISNUMBER(O249)),G249*O249,"") -> 6879.1731 | Q249: =IF(H249="","Missing price; ","")&IF(J249="UNKNOWN","Unknown item; ","")&IF(AND(ISNUMBER(N249),N249>Discount_Threshold),"Discount above limit; ","") | R249: =IF(Q249="","OK","CHECK") -> OK
A250: INV-25196 | B250: 45996 | C250: CUST-002 | D250: AB | E250: CA | F250: PC-MH-1050B | G250: 4 | H250: 883 | I250: =UPPER(TRIM(F250)) -> PC-MH-1050B | J250: =IFERROR(INDEX(Items!$C$2:$C$500,MATCH(I250,Items!$H$2:$H$500,0)),"UNKNOWN") -> Manhole | K250: =IF(J250="UNKNOWN","",INDEX(Items!$F$2:$F$500,MATCH(I250,Items!$H$2:$H$500,0))) -> 980 | L250: =IF(ISNUMBER(H250),G250*H250,"") -> 3532 | M250: =IF(ISNUMBER(H250),G250,0) -> 4 | N250: =IF(AND(ISNUMBER(H250),ISNUMBER(K250)),1-H250/K250,"") -> 0.098979592 | O250: =IF(J250="UNKNOWN","",INDEX(Cost_Rollup!$F$5:$F$16,MATCH(I250,Cost_Rollup!$A$5:$A$16,0))) -> 635.433 | P250: =IF(AND(ISNUMBER(L250),ISNUMBER(O250)),G250*O250,"") -> 2541.732 | Q250: =IF(H250="","Missing price; ","")&IF(J250="UNKNOWN","Unknown item; ","")&IF(AND(ISNUMBER(N250),N250>Discount_Threshold),"Discount above limit; ","") | R250: =IF(Q250="","OK","CHECK") -> OK
A251: INV-25110 | B251: 45999 | C251: CUST-008 | D251: ND | E251: US | F251: PC-MH-1200R | G251: 6 | H251: 480.87 | I251: =UPPER(TRIM(F251)) -> PC-MH-1200R | J251: =IFERROR(INDEX(Items!$C$2:$C$500,MATCH(I251,Items!$H$2:$H$500,0)),"UNKNOWN") -> Manhole | K251: =IF(J251="UNKNOWN","",INDEX(Items!$F$2:$F$500,MATCH(I251,Items!$H$2:$H$500,0))) -> 520 | L251: =IF(ISNUMBER(H251),G251*H251,"") -> 2885.22 | M251: =IF(ISNUMBER(H251),G251,0) -> 6 | N251: =IF(AND(ISNUMBER(H251),ISNUMBER(K251)),1-H251/K251,"") -> 0.07525 | O251: =IF(J251="UNKNOWN","",INDEX(Cost_Rollup!$F$5:$F$16,MATCH(I251,Cost_Rollup!$A$5:$A$16,0))) -> 381.98428 | P251: =IF(AND(ISNUMBER(L251),ISNUMBER(O251)),G251*O251,"") -> 2291.9057 | Q251: =IF(H251="","Missing price; ","")&IF(J251="UNKNOWN","Unknown item; ","")&IF(AND(ISNUMBER(N251),N251>Discount_Threshold),"Discount above limit; ","") | R251: =IF(Q251="","OK","CHECK") -> OK
A252: INV-25149 | B252: 45999 | C252: CUST-010 | D252: BC | E252: CA | F252: PC-RCP-0600 | G252: 29 | H252: 635.73 | I252: =UPPER(TRIM(F252)) -> PC-RCP-0600 | J252: =IFERROR(INDEX(Items!$C$2:$C$500,MATCH(I252,Items!$H$2:$H$500,0)),"UNKNOWN") -> Pipe | K252: =IF(J252="UNKNOWN","",INDEX(Items!$F$2:$F$500,MATCH(I252,Items!$H$2:$H$500,0))) -> 640 | L252: =IF(ISNUMBER(H252),G252*H252,"") -> 18436.17 | M252: =IF(ISNUMBER(H252),G252,0) -> 29 | N252: =IF(AND(ISNUMBER(H252),ISNUMBER(K252)),1-H252/K252,"") -> 0.006671875 | O252: =IF(J252="UNKNOWN","",INDEX(Cost_Rollup!$F$5:$F$16,MATCH(I252,Cost_Rollup!$A$5:$A$16,0))) -> 429.94832 | P252: =IF(AND(ISNUMBER(L252),ISNUMBER(O252)),G252*O252,"") -> 12468.501 | Q252: =IF(H252="","Missing price; ","")&IF(J252="UNKNOWN","Unknown item; ","")&IF(AND(ISNUMBER(N252),N252>Discount_Threshold),"Discount above limit; ","") | R252: =IF(Q252="","OK","CHECK") -> OK
A253: INV-25093 | B253: 46001 | C253: CUST-003 | D253: SK | E253: CA | F253: PC-BAR-F38 | G253: 11 | H253: 1322.36 | I253: =UPPER(TRIM(F253)) -> PC-BAR-F38 | J253: =IFERROR(INDEX(Items!$C$2:$C$500,MATCH(I253,Items!$H$2:$H$500,0)),"UNKNOWN") -> Barrier | K253: =IF(J253="UNKNOWN","",INDEX(Items!$F$2:$F$500,MATCH(I253,Items!$H$2:$H$500,0))) -> 1450 | L253: =IF(ISNUMBER(H253),G253*H253,"") -> 14545.96 | M253: =IF(ISNUMBER(H253),G253,0) -> 11 | N253: =IF(AND(ISNUMBER(H253),ISNUMBER(K253)),1-H253/K253,"") -> 0.088027586 | O253: =IF(J253="UNKNOWN","",INDEX(Cost_Rollup!$F$5:$F$16,MATCH(I253,Cost_Rollup!$A$5:$A$16,0))) -> 978.66328 | P253: =IF(AND(ISNUMBER(L253),ISNUMBER(O253)),G253*O253,"") -> 10765.296 | Q253: =IF(H253="","Missing price; ","")&IF(J253="UNKNOWN","Unknown item; ","")&IF(AND(ISNUMBER(N253),N253>Discount_Threshold),"Discount above limit; ","") | R253: =IF(Q253="","OK","CHECK") -> OK
A254: INV-25224 | B254: 46003 | C254: CUST-006 | D254: AB | E254: CA | F254: PC-RCP-1200 | G254: 29 | H254: 1727.86 | I254: =UPPER(TRIM(F254)) -> PC-RCP-1200 | J254: =IFERROR(INDEX(Items!$C$2:$C$500,MATCH(I254,Items!$H$2:$H$500,0)),"UNKNOWN") -> Pipe | K254: =IF(J254="UNKNOWN","",INDEX(Items!$F$2:$F$500,MATCH(I254,Items!$H$2:$H$500,0))) -> 1890 | L254: =IF(ISNUMBER(H254),G254*H254,"") -> 50107.94 | M254: =IF(ISNUMBER(H254),G254,0) -> 29 | N254: =IF(AND(ISNUMBER(H254),ISNUMBER(K254)),1-H254/K254,"") -> 0.08578836 | O254: =IF(J254="UNKNOWN","",INDEX(Cost_Rollup!$F$5:$F$16,MATCH(I254,Cost_Rollup!$A$5:$A$16,0))) -> 1206.4054 | P254: =IF(AND(ISNUMBER(L254),ISNUMBER(O254)),G254*O254,"") -> 34985.757 | Q254: =IF(H254="","Missing price; ","")&IF(J254="UNKNOWN","Unknown item; ","")&IF(AND(ISNUMBER(N254),N254>Discount_Threshold),"Discount above limit; ","") | R254: =IF(Q254="","OK","CHECK") -> OK
A255: INV-25053 | B255: 46006 | C255: CUST-003 | D255: SK | E255: CA | F255: PC-RCP-0600 | G255: 15 | H255: 651.85 | I255: =UPPER(TRIM(F255)) -> PC-RCP-0600 | J255: =IFERROR(INDEX(Items!$C$2:$C$500,MATCH(I255,Items!$H$2:$H$500,0)),"UNKNOWN") -> Pipe | K255: =IF(J255="UNKNOWN","",INDEX(Items!$F$2:$F$500,MATCH(I255,Items!$H$2:$H$500,0))) -> 640 | L255: =IF(ISNUMBER(H255),G255*H255,"") -> 9777.75 | M255: =IF(ISNUMBER(H255),G255,0) -> 15 | N255: =IF(AND(ISNUMBER(H255),ISNUMBER(K255)),1-H255/K255,"") -> -0.018515625 | O255: =IF(J255="UNKNOWN","",INDEX(Cost_Rollup!$F$5:$F$16,MATCH(I255,Cost_Rollup!$A$5:$A$16,0))) -> 429.94832 | P255: =IF(AND(ISNUMBER(L255),ISNUMBER(O255)),G255*O255,"") -> 6449.2248 | Q255: =IF(H255="","Missing price; ","")&IF(J255="UNKNOWN","Unknown item; ","")&IF(AND(ISNUMBER(N255),N255>Discount_Threshold),"Discount above limit; ","") | R255: =IF(Q255="","OK","CHECK") -> OK
A256: INV-25057 | B256: 46006 | C256: CUST-009 | D256: SK | E256: CA | F256: PC-RCP-1200 | G256: 7 | H256: 1907.8 | I256: =UPPER(TRIM(F256)) -> PC-RCP-1200 | J256: =IFERROR(INDEX(Items!$C$2:$C$500,MATCH(I256,Items!$H$2:$H$500,0)),"UNKNOWN") -> Pipe | K256: =IF(J256="UNKNOWN","",INDEX(Items!$F$2:$F$500,MATCH(I256,Items!$H$2:$H$500,0))) -> 1890 | L256: =IF(ISNUMBER(H256),G256*H256,"") -> 13354.6 | M256: =IF(ISNUMBER(H256),G256,0) -> 7 | N256: =IF(AND(ISNUMBER(H256),ISNUMBER(K256)),1-H256/K256,"") -> -0.0094179894 | O256: =IF(J256="UNKNOWN","",INDEX(Cost_Rollup!$F$5:$F$16,MATCH(I256,Cost_Rollup!$A$5:$A$16,0))) -> 1206.4054 | P256: =IF(AND(ISNUMBER(L256),ISNUMBER(O256)),G256*O256,"") -> 8444.8378 | Q256: =IF(H256="","Missing price; ","")&IF(J256="UNKNOWN","Unknown item; ","")&IF(AND(ISNUMBER(N256),N256>Discount_Threshold),"Discount above limit; ","") | R256: =IF(Q256="","OK","CHECK") -> OK
... A261: INV-25006 | B261: 46013 | C261: CUST-008 | D261: ND | E261: US | F261: PC-HC-200 | G261: 200 | H261: 109.67 | I261: =UPPER(TRIM(F261)) -> PC-HC-200 | J261: =IFERROR(INDEX(Items!$C$2:$C$500,MATCH(I261,Items!$H$2:$H$500,0)),"UNKNOWN") -> Slab | K261: =IF(J261="UNKNOWN","",INDEX(Items!$F$2:$F$500,MATCH(I261,Items!$H$2:$H$500,0))) -> 118 | L261: =IF(ISNUMBER(H261),G261*H261,"") -> 21934 | M261: =IF(ISNUMBER(H261),G261,0) -> 200 | N261: =IF(AND(ISNUMBER(H261),ISNUMBER(K261)),1-H261/K261,"") -> 0.07059322 | O261: =IF(J261="UNKNOWN","",INDEX(Cost_Rollup!$F$5:$F$16,MATCH(I261,Cost_Rollup!$A$5:$A$16,0))) -> 78.89382 | P261: =IF(AND(ISNUMBER(L261),ISNUMBER(O261)),G261*O261,"") -> 15778.764 | Q261: =IF(H261="","Missing price; ","")&IF(J261="UNKNOWN","Unknown item; ","")&IF(AND(ISNUMBER(N261),N261>Discount_Threshold),"Discount above limit; ","") | R261: =IF(Q261="","OK","CHECK") -> OK

Sheet Cost_Rollup
A1: Product Cost Roll-up
A2: Material cost from the BOM + estimated conversion cost, compared with 2025 average selling price.
A4: Item | B4: Description | C4: Category | D4: Material cost (CAD) | E4: Conversion cost (CAD) | F4: Total unit cost (CAD) | G4: List price (CAD) | H4: Avg selling price 2025 (CAD) | I4: Margin per unit (CAD) | J4: Margin % | K4: Cost-to-price ratio | L4: Domestic share of material cost | M4: BOM lines | N4: Lines to review | O4: Data status
A5: =Items!A2 -> PC-RCP-0600 | B5: =Items!B2 -> Reinforced concrete pipe 600 mm x 2.44 m | C5: =Items!C2 -> Pipe | D5: =SUMIFS(BOM!$L$2:$L$500,BOM!$A$2:$A$500,A5) -> 119.94832 | E5: =Items!G2 -> 310 | F5: =D5+E5 -> 429.94832 | G5: =Items!F2 -> 640 | H5: =IFERROR(SUMIFS(Sales!$L$2:$L$500,Sales!$I$2:$I$500,A5)/SUMIFS(Sales!$M$2:$M$500,Sales!$I$2:$I$500,A5),"") -> 622.57261 | I5: =IF(ISNUMBER(H5),H5-F5,"") -> 192.62429 | J5: =IF(ISNUMBER(H5),I5/H5,"") -> 0.30940052 | K5: =IF(ISNUMBER(H5),F5/H5,"") -> 0.69059948 | L5: =IF(D5>0,SUMIFS(BOM!$L$2:$L$500,BOM!$A$2:$A$500,A5,BOM!$N$2:$N$500,"Domestic")/D5,"") -> 0.7357502 | M5: =COUNTIF(BOM!$A$2:$A$500,A5) -> 9 | N5: =COUNTIFS(BOM!$A$2:$A$500,A5,BOM!$S$2:$S$500,"CHECK") -> 0 | O5: =IF(N5>0,"Incomplete","Complete") -> Complete
A6: =Items!A3 -> PC-RCP-0900 | B6: =Items!B3 -> Reinforced concrete pipe 900 mm x 2.44 m | C6: =Items!C3 -> Pipe | D6: =SUMIFS(BOM!$L$2:$L$500,BOM!$A$2:$A$500,A6) -> 210.43373 | E6: =Items!G3 -> 540 | F6: =D6+E6 -> 750.43373 | G6: =Items!F3 -> 1150 | H6: =IFERROR(SUMIFS(Sales!$L$2:$L$500,Sales!$I$2:$I$500,A6)/SUMIFS(Sales!$M$2:$M$500,Sales!$I$2:$I$500,A6),"") -> 1110.2925 | I6: =IF(ISNUMBER(H6),H6-F6,"") -> 359.85879 | J6: =IF(ISNUMBER(H6),I6/H6,"") -> 0.3241117 | K6: =IF(ISNUMBER(H6),F6/H6,"") -> 0.6758883 | L6: =IF(D6>0,SUMIFS(BOM!$L$2:$L$500,BOM!$A$2:$A$500,A6,BOM!$N$2:$N$500,"Domestic")/D6,"") -> 0.77513205 | M6: =COUNTIF(BOM!$A$2:$A$500,A6) -> 9 | N6: =COUNTIFS(BOM!$A$2:$A$500,A6,BOM!$S$2:$S$500,"CHECK") -> 0 | O6: =IF(N6>0,"Incomplete","Complete") -> Complete
A7: =Items!A4 -> PC-RCP-1200 | B7: =Items!B4 -> Reinforced concrete pipe 1200 mm x 2.44 m | C7: =Items!C4 -> Pipe | D7: =SUMIFS(BOM!$L$2:$L$500,BOM!$A$2:$A$500,A7) -> 346.4054 | E7: =Items!G4 -> 860 | F7: =D7+E7 -> 1206.4054 | G7: =Items!F4 -> 1890 | H7: =IFERROR(SUMIFS(Sales!$L$2:$L$500,Sales!$I$2:$I$500,A7)/SUMIFS(Sales!$M$2:$M$500,Sales!$I$2:$I$500,A7),"") -> 1794.6887 | I7: =IF(ISNUMBER(H7),H7-F7,"") -> 588.28327 | J7: =IF(ISNUMBER(H7),I7/H7,"") -> 0.32779127 | K7: =IF(ISNUMBER(H7),F7/H7,"") -> 0.67220873 | L7: =IF(D7>0,SUMIFS(BOM!$L$2:$L$500,BOM!$A$2:$A$500,A7,BOM!$N$2:$N$500,"Domestic")/D7,"") -> 0.77262075 | M7: =COUNTIF(BOM!$A$2:$A$500,A7) -> 10 | N7: =COUNTIFS(BOM!$A$2:$A$500,A7,BOM!$S$2:$S$500,"CHECK") -> 1 | O7: =IF(N7>0,"Incomplete","Complete") -> Incomplete
A8: =Items!A5 -> PC-BOX-1812 | B8: =Items!B5 -> Box culvert section 1.8 m x 1.2 m x 1.8 m | C8: =Items!C5 -> Box Culvert | D8: =SUMIFS(BOM!$L$2:$L$500,BOM!$A$2:$A$500,A8) -> 845.3624 | E8: =Items!G5 -> 1950 | F8: =D8+E8 -> 2795.3624 | G8: =Items!F5 -> 4200 | H8: =IFERROR(SUMIFS(Sales!$L$2:$L$500,Sales!$I$2:$I$500,A8)/SUMIFS(Sales!$M$2:$M$500,Sales!$I$2:$I$500,A8),"") -> 3972.33 | I8: =IF(ISNUMBER(H8),H8-F8,"") -> 1176.9676 | J8: =IF(ISNUMBER(H8),I8/H8,"") -> 0.2962915 | K8: =IF(ISNUMBER(H8),F8/H8,"") -> 0.7037085 | L8: =IF(D8>0,SUMIFS(BOM!$L$2:$L$500,BOM!$A$2:$A$500,A8,BOM!$N$2:$N$500,"Domestic")/D8,"") -> 0.52408293 | M8: =COUNTIF(BOM!$A$2:$A$500,A8) -> 11 | N8: =COUNTIFS(BOM!$A$2:$A$500,A8,BOM!$S$2:$S$500,"CHECK") -> 1 | O8: =IF(N8>0,"Incomplete","Complete") -> Incomplete
A9: =Items!A6 -> PC-MH-1050B | B9: =Items!B6 -> Manhole base 1050 mm | C9: =Items!C6 -> Manhole | D9: =SUMIFS(BOM!$L$2:$L$500,BOM!$A$2:$A$500,A9) -> 165.433 | E9: =Items!G6 -> 470 | F9: =D9+E9 -> 635.433 | G9: =Items!F6 -> 980 | H9: =IFERROR(SUMIFS(Sales!$L$2:$L$500,Sales!$I$2:$I$500,A9)/SUMIFS(Sales!$M$2:$M$500,Sales!$I$2:$I$500,A9),"") -> 929.32103 | I9: =IF(ISNUMBER(H9),H9-F9,"") -> 293.88803 | J9: =IF(ISNUMBER(H9),I9/H9,"") -> 0.31623951 | K9: =IF(ISNUMBER(H9),F9/H9,"") -> 0.68376049 | L9: =IF(D9>0,SUMIFS(BOM!$L$2:$L$500,BOM!$A$2:$A$500,A9,BOM!$N$2:$N$500,"Domestic")/D9,"") -> 0.84080867 | M9: =COUNTIF(BOM!$A$2:$A$500,A9) -> 9 | N9: =COUNTIFS(BOM!$A$2:$A$500,A9,BOM!$S$2:$S$500,"CHECK") -> 0 | O9: =IF(N9>0,"Incomplete","Complete") -> Complete
A10: =Items!A7 -> PC-MH-1200B | B10: =Items!B7 -> Manhole base 1200 mm | C10: =Items!C7 -> Manhole | D10: =SUMIFS(BOM!$L$2:$L$500,BOM!$A$2:$A$500,A10) -> 153.4208 | E10: =Items!G7 -> 600 | F10: =D10+E10 -> 753.4208 | G10: =Items!F7 -> 1240 | H10: =IFERROR(SUMIFS(Sales!$L$2:$L$500,Sales!$I$2:$I$500,A10)/SUMIFS(Sales!$M$2:$M$500,Sales!$I$2:$I$500,A10),"") -> 1207.0384 | I10: =IF(ISNUMBER(H10),H10-F10,"") -> 453.61755 | J10: =IF(ISNUMBER(H10),I10/H10,"") -> 0.37581039 | K10: =IF(ISNUMBER(H10),F10/H10,"") -> 0.62418961 | L10: =IF(D10>0,SUMIFS(BOM!$L$2:$L$500,BOM!$A$2:$A$500,A10,BOM!$N$2:$N$500,"Domestic")/D10,"") -> 0.80655622 | M10: =COUNTIF(BOM!$A$2:$A$500,A10) -> 9 | N10: =COUNTIFS(BOM!$A$2:$A$500,A10,BOM!$S$2:$S$500,"CHECK") -> 1 | O10: =IF(N10>0,"Incomplete","Complete") -> Incomplete
A11: =Items!A8 -> PC-MH-1200R | B11: =Items!B8 -> Manhole riser 1200 mm x 600 mm | C11: =Items!C8 -> Manhole | D11: =SUMIFS(BOM!$L$2:$L$500,BOM!$A$2:$A$500,A11) -> 81.98428 | E11: =Items!G8 -> 300 | F11: =D11+E11 -> 381.98428 | G11: =Items!F8 -> 520 | H11: =IFERROR(SUMIFS(Sales!$L$2:$L$500,Sales!$I$2:$I$500,A11)/SUMIFS(Sales!$M$2:$M$500,Sales!$I$2:$I$500,A11),"") -> 506.72322 | I11: =IF(ISNUMBER(H11),H11-F11,"") -> 124.73894 | J11: =IF(ISNUMBER(H11),I11/H11,"") -> 0.2461678 | K11: =IF(ISNUMBER(H11),F11/H11,"") -> 0.7538322 | L11: =IF(D11>0,SUMIFS(BOM!$L$2:$L$500,BOM!$A$2:$A$500,A11,BOM!$N$2:$N$500,"Domestic")/D11,"") -> 0.66839643 | M11: =COUNTIF(BOM!$A$2:$A$500,A11) -> 9 | N11: =COUNTIFS(BOM!$A$2:$A$500,A11,BOM!$S$2:$S$500,"CHECK") -> 1 | O11: =IF(N11>0,"Incomplete","Complete") -> Incomplete
A12: =Items!A9 -> PC-CB-0600 | B12: =Items!B9 -> Catch basin 600 mm x 600 mm | C12: =Items!C9 -> Catch Basin | D12: =SUMIFS(BOM!$L$2:$L$500,BOM!$A$2:$A$500,A12) -> 301.0488 | E12: =Items!G9 -> 170 | F12: =D12+E12 -> 471.0488 | G12: =Items!F9 -> 690 | H12: =IFERROR(SUMIFS(Sales!$L$2:$L$500,Sales!$I$2:$I$500,A12)/SUMIFS(Sales!$M$2:$M$500,Sales!$I$2:$I$500,A12),"") -> 668.00837 | I12: =IF(ISNUMBER(H12),H12-F12,"") -> 196.95957 | J12: =IF(ISNUMBER(H12),I12/H12,"") -> 0.29484596 | K12: =IF(ISNUMBER(H12),F12/H12,"") -> 0.70515404 | L12: =IF(D12>0,SUMIFS(BOM!$L$2:$L$500,BOM!$A$2:$A$500,A12,BOM!$N$2:$N$500,"Domestic")/D12,"") -> 0.27745502 | M12: =COUNTIF(BOM!$A$2:$A$500,A12) -> 9 | N12: =COUNTIFS(BOM!$A$2:$A$500,A12,BOM!$S$2:$S$500,"CHECK") -> 0 | O12: =IF(N12>0,"Incomplete","Complete") -> Complete
A13: =Items!A10 -> PC-BAR-F38 | B13: =Items!B10 -> F-shape traffic barrier 3.8 m | C13: =Items!C10 -> Barrier | D13: =SUMIFS(BOM!$L$2:$L$500,BOM!$A$2:$A$500,A13) -> 328.66328 | E13: =Items!G10 -> 650 | F13: =D13+E13 -> 978.66328 | G13: =Items!F10 -> 1450 | H13: =IFERROR(SUMIFS(Sales!$L$2:$L$500,Sales!$I$2:$I$500,A13)/SUMIFS(Sales!$M$2:$M$500,Sales!$I$2:$I$500,A13),"") -> 1408.0405 | I13: =IF(ISNUMBER(H13),H13-F13,"") -> 429.37718 | J13: =IF(ISNUMBER(H13),I13/H13,"") -> 0.30494662 | K13: =IF(ISNUMBER(H13),F13/H13,"") -> 0.69505338 | L13: =IF(D13>0,SUMIFS(BOM!$L$2:$L$500,BOM!$A$2:$A$500,A13,BOM!$N$2:$N$500,"Domestic")/D13,"") -> 0.88071293 | M13: =COUNTIF(BOM!$A$2:$A$500,A13) -> 9 | N13: =COUNTIFS(BOM!$A$2:$A$500,A13,BOM!$S$2:$S$500,"CHECK") -> 0 | O13: =IF(N13>0,"Incomplete","Complete") -> Complete
A14: =Items!A11 -> PC-BAR-SS60 | B14: =Items!B11 -> Single-slope traffic barrier 6.0 m | C14: =Items!C11 -> Barrier | D14: =SUMIFS(BOM!$L$2:$L$500,BOM!$A$2:$A$500,A14) -> 603.5454 | E14: =Items!G11 -> 980 | F14: =D14+E14 -> 1583.5454 | G14: =Items!F11 -> 2350 | H14: =IFERROR(SUMIFS(Sales!$L$2:$L$500,Sales!$I$2:$I$500,A14)/SUMIFS(Sales!$M$2:$M$500,Sales!$I$2:$I$500,A14),"") -> 2275.6626 | I14: =IF(ISNUMBER(H14),H14-F14,"") -> 692.11723 | J14: =IF(ISNUMBER(H14),I14/H14,"") -> 0.30413877 | K14: =IF(ISNUMBER(H14),F14/H14,"") -> 0.69586123 | L14: =IF(D14>0,SUMIFS(BOM!$L$2:$L$500,BOM!$A$2:$A$500,A14,BOM!$N$2:$N$500,"Domestic")/D14,"") -> 0.8206922 | M14: =COUNTIF(BOM!$A$2:$A$500,A14) -> 11 | N14: =COUNTIFS(BOM!$A$2:$A$500,A14,BOM!$S$2:$S$500,"CHECK") -> 1 | O14: =IF(N14>0,"Incomplete","Complete") -> Incomplete
A15: =Items!A12 -> PC-HC-200 | B15: =Items!B12 -> Hollow-core slab 200 mm (per m2) | C15: =Items!C12 -> Slab | D15: =SUMIFS(BOM!$L$2:$L$500,BOM!$A$2:$A$500,A15) -> 26.89382 | E15: =Items!G12 -> 52 | F15: =D15+E15 -> 78.89382 | G15: =Items!F12 -> 118 | H15: =IFERROR(SUMIFS(Sales!$L$2:$L$500,Sales!$I$2:$I$500,A15)/SUMIFS(Sales!$M$2:$M$500,Sales!$I$2:$I$500,A15),"") -> 115.2015 | I15: =IF(ISNUMBER(H15),H15-F15,"") -> 36.307679 | J15: =IF(ISNUMBER(H15),I15/H15,"") -> 0.31516672 | K15: =IF(ISNUMBER(H15),F15/H15,"") -> 0.68483328 | L15: =IF(D15>0,SUMIFS(BOM!$L$2:$L$500,BOM!$A$2:$A$500,A15,BOM!$N$2:$N$500,"Domestic")/D15,"") -> 0.62884336 | M15: =COUNTIF(BOM!$A$2:$A$500,A15) -> 8 | N15: =COUNTIFS(BOM!$A$2:$A$500,A15,BOM!$S$2:$S$500,"CHECK") -> 0 | O15: =IF(N15>0,"Incomplete","Complete") -> Complete
A16: =Items!A13 -> PC-HC-250 | B16: =Items!B13 -> Hollow-core slab 250 mm (per m2) | C16: =Items!C13 -> Slab | D16: =SUMIFS(BOM!$L$2:$L$500,BOM!$A$2:$A$500,A16) -> 32.94024 | E16: =Items!G13 -> 60 | F16: =D16+E16 -> 92.94024 | G16: =Items!F13 -> 136 | H16: =IFERROR(SUMIFS(Sales!$L$2:$L$500,Sales!$I$2:$I$500,A16)/SUMIFS(Sales!$M$2:$M$500,Sales!$I$2:$I$500,A16),"") -> 133.72619 | I16: =IF(ISNUMBER(H16),H16-F16,"") -> 40.785946 | J16: =IF(ISNUMBER(H16),I16/H16,"") -> 0.30499596 | K16: =IF(ISNUMBER(H16),F16/H16,"") -> 0.69500404 | L16: =IF(D16>0,SUMIFS(BOM!$L$2:$L$500,BOM!$A$2:$A$500,A16,BOM!$N$2:$N$500,"Domestic")/D16,"") -> 0.63184118 | M16: =COUNTIF(BOM!$A$2:$A$500,A16) -> 8 | N16: =COUNTIFS(BOM!$A$2:$A$500,A16,BOM!$S$2:$S$500,"CHECK") -> 0 | O16: =IF(N16>0,"Incomplete","Complete") -> Complete
A18: Note: 'Incomplete' items have BOM lines to review (missing cost, origin or part number). A missing cost means material cost is understated. See BOM (status = CHECK).

Sheet Sourcing
A1: Sourcing Analysis (2025)
A2: Material spend = BOM extended cost x units sold in 2025. Shows where purchased material comes from.
A4: Origin country | B4: Material spend 2025 (CAD) | C4: Share of spend | D4: BOM lines | F4: Supplier | G4: Supplier name | H4: Country | I4: Lead time (days) | J4: Material spend 2025 (CAD) | K4: Share of spend | L4: Lead time flag
A5: CA | B5: =SUMIFS(BOM!$Q$2:$Q$500,BOM!$M$2:$M$500,A5) -> 1007765.7 | C5: =IF($B$13>0,B5/$B$13,0) -> 0.73965443 | D5: =COUNTIF(BOM!$M$2:$M$500,A5) -> 59 | F5: =Suppliers!A2 -> SUP-01 | G5: =Suppliers!B2 -> Prairie Cement Co. | H5: =Suppliers!C2 -> CA | I5: =Suppliers!E2 -> 7 | J5: =SUMIFS(BOM!$Q$2:$Q$500,BOM!$O$2:$O$500,F5) -> 453017.37 | K5: =IF($B$13>0,J5/$B$13,0) -> 0.33249425 | L5: =Suppliers!F2
A6: US | B6: =SUMIFS(BOM!$Q$2:$Q$500,BOM!$M$2:$M$500,A6) -> 93872.512 | C6: =IF($B$13>0,B6/$B$13,0) -> 0.068898175 | D6: =COUNTIF(BOM!$M$2:$M$500,A6) -> 37 | F6: =Suppliers!A3 -> SUP-02 | G6: =Suppliers!B3 -> Great Plains Ash Inc. | H6: =Suppliers!C3 -> US | I6: =Suppliers!E3 -> 14 | J6: =SUMIFS(BOM!$Q$2:$Q$500,BOM!$O$2:$O$500,F6) -> 38030.326 | K6: =IF($B$13>0,J6/$B$13,0) -> 0.027912538 | L6: =Suppliers!F3
A7: MX | B7: =SUMIFS(BOM!$Q$2:$Q$500,BOM!$M$2:$M$500,A7) -> 21299.39 | C7: =IF($B$13>0,B7/$B$13,0) -> 0.015632788 | D7: =COUNTIF(BOM!$M$2:$M$500,A7) -> 2 | F7: =Suppliers!A4 -> SUP-03 | G7: =Suppliers!B4 -> Red Valley Aggregates | H7: =Suppliers!C4 -> CA | I7: =Suppliers!E4 -> 3 | J7: =SUMIFS(BOM!$Q$2:$Q$500,BOM!$O$2:$O$500,F7) -> 261070.19 | K7: =IF($B$13>0,J7/$B$13,0) -> 0.19161371 | L7: =Suppliers!F4
A8: TR | B8: =SUMIFS(BOM!$Q$2:$Q$500,BOM!$M$2:$M$500,A8) -> 77541.726 | C8: =IF($B$13>0,B8/$B$13,0) -> 0.056912117 | D8: =COUNTIF(BOM!$M$2:$M$500,A8) -> 2 | F8: =Suppliers!A5 -> SUP-04 | G8: =Suppliers!B5 -> Midwest Admix Solutions | H8: =Suppliers!C5 -> US | I8: =Suppliers!E5 -> 10 | J8: =SUMIFS(BOM!$Q$2:$Q$500,BOM!$O$2:$O$500,F8) -> 54027.21 | K8: =IF($B$13>0,J8/$B$13,0) -> 0.039653527 | L8: =Suppliers!F5
A9: KR | B9: =SUMIFS(BOM!$Q$2:$Q$500,BOM!$M$2:$M$500,A9) -> 71093.958 | C9: =IF($B$13>0,B9/$B$13,0) -> 0.052179747 | D9: =COUNTIF(BOM!$M$2:$M$500,A9) -> 2 | F9: =Suppliers!A6 -> SUP-05 | G9: =Suppliers!B6 -> Northern Rebar Mills | H9: =Suppliers!C6 -> CA | I9: =Suppliers!E6 -> 10 | J9: =SUMIFS(BOM!$Q$2:$Q$500,BOM!$O$2:$O$500,F9) -> 291095.13 | K9: =IF($B$13>0,J9/$B$13,0) -> 0.21365065 | L9: =Suppliers!F6
A10: DE | B10: =SUMIFS(BOM!$Q$2:$Q$500,BOM!$M$2:$M$500,A10) -> 31312.2 | C10: =IF($B$13>0,B10/$B$13,0) -> 0.022981738 | D10: =COUNTIF(BOM!$M$2:$M$500,A10) -> 6 | F10: =Suppliers!A7 -> SUP-06 | G10: =Suppliers!B7 -> Anatolia Steel Trading | H10: =Suppliers!C7 -> TR | I10: =Suppliers!E7 -> 60 | J10: =SUMIFS(BOM!$Q$2:$Q$500,BOM!$O$2:$O$500,F10) -> 77541.726 | K10: =IF($B$13>0,J10/$B$13,0) -> 0.056912117 | L10: =Suppliers!F7 -> Long lead time
A11: IN | B11: =SUMIFS(BOM!$Q$2:$Q$500,BOM!$M$2:$M$500,A11) -> 36120 | C11: =IF($B$13>0,B11/$B$13,0) -> 0.026510445 | D11: =COUNTIF(BOM!$M$2:$M$500,A11) -> 1 | F11: =Suppliers!A8 -> SUP-07 | G11: =Suppliers!B8 -> Lakeside Wire Products | H11: =Suppliers!C8 -> US | I11: =Suppliers!E8 -> 14 | J11: =SUMIFS(BOM!$Q$2:$Q$500,BOM!$O$2:$O$500,F11) -> 1814.976 | K11: =IF($B$13>0,J11/$B$13,0) -> 0.0013321102 | L11: =Suppliers!F8
A12: UNKNOWN | B12: =SUMIFS(BOM!$Q$2:$Q$500,BOM!$M$2:$M$500,A12) -> 23476.32 | C12: =IF($B$13>0,B12/$B$13,0) -> 0.017230556 | D12: =COUNTIF(BOM!$M$2:$M$500,A12) -> 1 | F12: =Suppliers!A9 -> SUP-08 | G12: =Suppliers!B9 -> Hanbit Strand Co. | H12: =Suppliers!C9 -> KR | I12: =Suppliers!E9 -> 55 | J12: =SUMIFS(BOM!$Q$2:$Q$500,BOM!$O$2:$O$500,F12) -> 71093.958 | K12: =IF($B$13>0,J12/$B$13,0) -> 0.052179747 | L12: =Suppliers!F9 -> Long lead time
A13: Total costed spend | B13: =SUM(B5:B12) -> 1362481.8 | C13: =SUM(C5:C12) -> 1 | D13: =SUM(D5:D12) -> 110 | F13: =Suppliers!A10 -> SUP-09 | G13: =Suppliers!B10 -> Sierra Rubber Works | H13: =Suppliers!C10 -> MX | I13: =Suppliers!E10 -> 21 | J13: =SUMIFS(BOM!$Q$2:$Q$500,BOM!$O$2:$O$500,F13) -> 44775.71 | K13: =IF($B$13>0,J13/$B$13,0) -> 0.032863344 | L13: =Suppliers!F10
A14: Check: all BOM spend | B14: =SUM(BOM!$Q$2:$Q$500) -> 1362481.8 | F14: =Suppliers!A11 -> SUP-10 | G14: =Suppliers!B11 -> Rhein Lifting Systems | H14: =Suppliers!C11 -> DE | I14: =Suppliers!E11 -> 45 | J14: =SUMIFS(BOM!$Q$2:$Q$500,BOM!$O$2:$O$500,F14) -> 31312.2 | K14: =IF($B$13>0,J14/$B$13,0) -> 0.022981738 | L14: =Suppliers!F11 -> Long lead time
A15: Difference (should be 0) | B15: =B14-B13 -> 0 | F15: =Suppliers!A12 -> SUP-12 | G15: =Suppliers!B12 -> Westway Site Supply | H15: =Suppliers!C12 -> CA | I15: =Suppliers!E12 -> 5 | J15: =SUMIFS(BOM!$Q$2:$Q$500,BOM!$O$2:$O$500,F15) -> 2583.038 | K15: =IF($B$13>0,J15/$B$13,0) -> 0.001895833 | L15: =Suppliers!F12
A16: If the difference is not 0, add the missing country code to column A. | F16: (other) | G16: Not in supplier list | J16: =B13-SUM(J5:J15) -> 36120 | K16: =IF($B$13>0,J16/$B$13,0) -> 0.026510445
F17: Total | J17: =SUM(J5:J16) -> 1362481.8 | K17: =SUM(K5:K16) -> 1

Sheet Summary
A1: Sales and Margin Summary (2025)
A2: Built with SUMIFS. A PivotTable version is one of the exercises in docs/EXERCISES.md.
A3: Key figures
A4: Revenue, all priced lines (CAD) | B4: =SUM(Sales!$L$2:$L$500) -> 5848270.8
A5: Revenue with known cost (CAD) | B5: =SUMIFS(Sales!$L$2:$L$500,Sales!$J$2:$J$500,"<>UNKNOWN") -> 5829080.7
A6: Cost of sales (CAD) | B6: =SUM(Sales!$P$2:$P$500) -> 4016884.3
A7: Gross margin (CAD) | B7: =B5-B6 -> 1812196.5
A8: Gross margin % | B8: =IF(B5>0,B7/B5,0) -> 0.31088889
A9: Units shipped | B9: =SUM(Sales!$G$2:$G$500) -> 11577
A10: Invoice lines | B10: =COUNTA(Sales!$A$2:$A$500) -> 260
A11: Invoice lines to review | B11: =COUNTIF(Sales!$R$2:$R$500,"CHECK") -> 5
A13: By product category
A14: Category | B14: Units | C14: Revenue (CAD) | D14: Cost of sales (CAD) | E14: Gross margin (CAD) | F14: GM %
A15: Pipe | B15: =SUMIFS(Sales!$G$2:$G$500,Sales!$J$2:$J$500,A15) -> 1196 | C15: =SUMIFS(Sales!$L$2:$L$500,Sales!$J$2:$J$500,A15) -> 1499415 | D15: =SUMIFS(Sales!$P$2:$P$500,Sales!$J$2:$J$500,A15) -> 1013094.6 | E15: =C15-D15 -> 486320.44 | F15: =IF(C15>0,E15/C15,0) -> 0.32434012
A16: Box Culvert | B16: =SUMIFS(Sales!$G$2:$G$500,Sales!$J$2:$J$500,A16) -> 127 | C16: =SUMIFS(Sales!$L$2:$L$500,Sales!$J$2:$J$500,A16) -> 504485.91 | D16: =SUMIFS(Sales!$P$2:$P$500,Sales!$J$2:$J$500,A16) -> 355011.02 | E16: =C16-D16 -> 149474.89 | F16: =IF(C16>0,E16/C16,0) -> 0.2962915
A17: Manhole | B17: =SUMIFS(Sales!$G$2:$G$500,Sales!$J$2:$J$500,A17) -> 259 | C17: =SUMIFS(Sales!$L$2:$L$500,Sales!$J$2:$J$500,A17) -> 227932.62 | D17: =SUMIFS(Sales!$P$2:$P$500,Sales!$J$2:$J$500,A17) -> 152503.65 | E17: =C17-D17 -> 75428.968 | F17: =IF(C17>0,E17/C17,0) -> 0.3309266
A18: Catch Basin | B18: =SUMIFS(Sales!$G$2:$G$500,Sales!$J$2:$J$500,A18) -> 172 | C18: =SUMIFS(Sales!$L$2:$L$500,Sales!$J$2:$J$500,A18) -> 114897.44 | D18: =SUMIFS(Sales!$P$2:$P$500,Sales!$J$2:$J$500,A18) -> 81020.394 | E18: =C18-D18 -> 33877.046 | F18: =IF(C18>0,E18/C18,0) -> 0.29484596
A19: Barrier | B19: =SUMIFS(Sales!$G$2:$G$500,Sales!$J$2:$J$500,A19) -> 1342 | C19: =SUMIFS(Sales!$L$2:$L$500,Sales!$J$2:$J$500,A19) -> 2493455.3 | D19: =SUMIFS(Sales!$P$2:$P$500,Sales!$J$2:$J$500,A19) -> 1734364.1 | E19: =C19-D19 -> 759091.25 | F19: =IF(C19>0,E19/C19,0) -> 0.30443347
A20: Slab | B20: =SUMIFS(Sales!$G$2:$G$500,Sales!$J$2:$J$500,A20) -> 8470 | C20: =SUMIFS(Sales!$L$2:$L$500,Sales!$J$2:$J$500,A20) -> 988894.4 | D20: =SUMIFS(Sales!$P$2:$P$500,Sales!$J$2:$J$500,A20) -> 680890.54 | E20: =C20-D20 -> 308003.86 | F20: =IF(C20>0,E20/C20,0) -> 0.31146285
A21: Total | B21: =SUM(B15:B20) -> 11566 | C21: =SUM(C15:C20) -> 5829080.7 | D21: =SUM(D15:D20) -> 4016884.3 | E21: =SUM(E15:E20) -> 1812196.5 | F21: =IF(C21>0,E21/C21,0) -> 0.31088889
A22: Totals exclude invoice lines for unknown items. Items with incomplete BOM costs overstate margin.
A24: By ship-to country
A25: Country | B25: Units | C25: Revenue (CAD) | D25: Share of revenue
A26: CA | B26: =SUMIFS(Sales!$G$2:$G$500,Sales!$E$2:$E$500,A26) -> 9407 | C26: =SUMIFS(Sales!$L$2:$L$500,Sales!$E$2:$E$500,A26) -> 4909239.5 | D26: =IF($B$4>0,C26/$B$4,0) -> 0.83943436
A27: US | B27: =SUMIFS(Sales!$G$2:$G$500,Sales!$E$2:$E$500,A27) -> 2170 | C27: =SUMIFS(Sales!$L$2:$L$500,Sales!$E$2:$E$500,A27) -> 939031.32 | D27: =IF($B$4>0,C27/$B$4,0) -> 0.16056564

Sheet Data_Quality
A1: Data Quality Checks
A2: Each check counts flagged rows on its source sheet. Filter that sheet's 'status' column to CHECK to see them.
A4: ID | B4: Sheet | C4: Check | D4: How it is tested | E4: Rows flagged | F4: Severity | G4: Suggested action
A5: DQ-01 | B5: Items | C5: HS code missing or wrong format | D5: Blank, not 7 characters, or no dot in position 5 (####.##) | E5: =COUNTIF(Items!$I$2:$I$500,"*HS code*") -> 1 | F5: Medium | G5: Confirm HS code with the product team
A6: DQ-02 | B6: Components | C6: Unit cost missing | D6: unit_cost is blank | E6: =COUNTIF(Components!$M$2:$M$500,"*Missing cost*") -> 1 | F6: High | G6: Get latest purchase price from purchasing
A7: DQ-03 | B7: Components | C7: Country of origin missing | D7: origin_country is blank | E7: =COUNTIF(Components!$M$2:$M$500,"*Missing origin*") -> 1 | F7: High | G7: Request origin information from the supplier
A8: DQ-04 | B8: Components | C8: Supplier not in supplier list | D8: supplier_id has no match on Suppliers | E8: =COUNTIF(Components!$M$2:$M$500,"*Unknown supplier*") -> 1 | F8: Medium | G8: Add the supplier or correct the ID
A9: DQ-05 | B9: Components | C9: Duplicate component code | D9: Same code after TRIM + UPPER appears more than once | E9: =COUNTIF(Components!$M$2:$M$500,"*Duplicate*") -> 2 | F9: High | G9: Keep one record; confirm which cost is current
A10: DQ-06 | B10: Components | C10: HS code format | D10: Blank, not 7 characters, or no dot in position 5 | E10: =COUNTIF(Components!$M$2:$M$500,"*HS code*") -> 1 | F10: Low | G10: Correct the format (####.##)
A11: DQ-07 | B11: BOM | C11: Component code not found | D11: comp_key has no match on Components | E11: =COUNTIF(BOM!$R$2:$R$500,"*Unknown component*") -> 1 | F11: High | G11: Ask engineering for the correct part number
A12: DQ-08 | B12: BOM | C12: No unit conversion available | D12: BOM unit differs from component unit and no factor exists | E12: =COUNTIF(BOM!$R$2:$R$500,"*No unit conversion*") -> 0 | F12: High | G12: Add the factor on Assumptions
A13: DQ-09 | B13: BOM | C13: Line has no cost | D13: Component found but its unit cost is blank | E13: =COUNTIF(BOM!$R$2:$R$500,"*Missing cost*") -> 3 | F13: High | G13: Fix the component cost (see Components)
A14: DQ-10 | B14: BOM | C14: Line has no country of origin | D14: Component found but origin is blank | E14: =COUNTIF(BOM!$R$2:$R$500,"*Missing origin*") -> 1 | F14: Medium | G14: Fix the component origin (see Components)
A15: DQ-11 | B15: BOM | C15: Unit converted automatically (info) | D15: BOM unit differs from component unit; factor applied | E15: =SUMPRODUCT((BOM!$E$2:$E$500<>BOM!$H$2:$H$500)*(BOM!$H$2:$H$500<>"")) -> 1 | F15: Info | G15: Confirm the BOM unit is intended (e.g. LB vs KG)
A16: DQ-12 | B16: BOM | C16: Code cleaned by TRIM/UPPER (info) | D16: Original code differs from cleaned key (case or spaces) | E16: =SUMPRODUCT((BOM!$C$2:$C$500<>"")*NOT(EXACT(BOM!$C$2:$C$500,BOM!$F$2:$F$500))) -> 1 | F16: Info | G16: Standardise the code in the source system
A17: DQ-13 | B17: Sales | C17: Unit price missing | D17: unit_price_cad is blank | E17: =COUNTIF(Sales!$Q$2:$Q$500,"*Missing price*") -> 2 | F17: High | G17: Check the invoice in the ERP
A18: DQ-14 | B18: Sales | C18: Item not in item list | D18: item_no has no match on Items | E18: =COUNTIF(Sales!$Q$2:$Q$500,"*Unknown item*") -> 1 | F18: High | G18: Add the item or correct the item number
A19: DQ-15 | B19: Sales | C19: Discount above limit | D19: Price is more than the Assumptions threshold below list price | E19: =COUNTIF(Sales!$Q$2:$Q$500,"*Discount*") -> 2 | F19: Medium | G19: Confirm the discount was approved
C21: Rows with status CHECK, by sheet
C22: Items | E22: =COUNTIF(Items!$J$2:$J$500,"CHECK") -> 1
C23: Components | E23: =COUNTIF(Components!$N$2:$N$500,"CHECK") -> 6
C24: BOM | E24: =COUNTIF(BOM!$S$2:$S$500,"CHECK") -> 5
C25: Sales | E25: =COUNTIF(Sales!$R$2:$R$500,"CHECK") -> 5

Sheet Open_Questions
A1: Open Questions Log
A2: Questions raised by the data checks. Update status and answer as information arrives.
A4: Q# | B4: Date raised | C4: Related check | D4: Item / component | E4: Question | F4: Ask | G4: Status | H4: Answer / notes
A5: Q01 | B5: 46316 | C5: DQ-03 | D5: GSK-1200 | E5: What is the country of origin for the 1200 mm gasket? Request a supplier declaration. | F5: Purchasing | G5: Open
A6: Q02 | B6: 46316 | C6: DQ-02 | D6: SEAL-BUT | E6: What is the current purchase price for butyl joint sealant (per metre)? | F6: Purchasing | G6: Open
A7: Q03 | B7: 46316 | C7: DQ-04 | D7: CST-FRM | E7: Supplier SUP-11 is not in the supplier list. Is this a new vendor or a wrong ID? | F7: Purchasing | G7: Open
A8: Q04 | B8: 46316 | C8: DQ-05 | D8: RB-15M | E8: Two records exist for RB-15M ($1.31 and $1.29/kg). Which price is current? | F8: Purchasing | G8: Open
A9: Q05 | B9: 46316 | C9: DQ-07 | D9: PC-MH-1200B | E9: BOM uses RB-12M, which does not exist. Should it be RB-10M or RB-15M? | F9: Engineering | G9: Open
A10: Q06 | B10: 46316 | C10: DQ-11 | D10: PC-RCP-0900 | E10: Rebar quantity is in LB, other BOMs use KG. Is 121 lb (about 55 kg) correct? | F10: Engineering | G10: Open
A11: Q07 | B11: 46316 | C11: DQ-01 | D11: PC-HC-250 | E11: HS code is missing for the 250 mm hollow-core slab. Confirm the classification. | F11: Product team | G11: Open
A12: Q08 | B12: 46316 | C12: DQ-14 | D12: PC-RCP-0750 | E12: Invoice lists item PC-RCP-0750, which is not in the item list. New product or typo? | F12: Sales | G12: Open
A13: Q09 | B13: 46316 | C13: DQ-15 | D13: (2 invoices) | E13: Two invoices are priced 30-38% below list price. Were these discounts approved? | F13: Sales | G13: Open
A14: Q10 | B14: 46316 | C14: DQ-13 | D14: (2 invoices) | E14: Two invoice lines have no unit price. Can the price be confirmed from the ERP? | F14: Accounting | G14: Open
